{"version": 0.6, "generator": "Overpass API 0.7.62.7 375dc00a", "osm3s": {"timestamp_osm_base": "2025-08-10T03:47:26Z", "copyright": "The data included in this document is from www.openstreetmap.org. The data is made available under ODbL."}, "elements": [{"type": "node", "id": 57971429, "lat": 40.594266, "lon": -121.095987}, {"type": "node", "id": 57980364, "lat": 40.753535, "lon": -121.252647}, {"type": "node", "id": 58052716, "lat": 40.6518387, "lon": -121.2111409}, {"type": "node", "id": 58060586, "lat": 40.6937527, "lon": -121.2024303}, {"type": "node", "id": 58060654, "lat": 40.6414632, "lon": -121.2252367}, {"type": "node", "id": 58087226, "lat": 40.6428362, "lon": -121.2410437}, {"type": "node", "id": 58087390, "lat": 40.6435164, "lon": -121.2478627}, {"type": "node", "id": 58141307, "lat": 40.646329, "lon": -121.284119}, {"type": "node", "id": 58141568, "lat": 40.6442667, "lon": -121.257492}, {"type": "node", "id": 58144391, "lat": 40.5832114, "lon": -121.2671662}, {"type": "node", "id": 58144392, "lat": 40.582582, "lon": -121.266799}, {"type": "node", "id": 58144395, "lat": 40.582108, "lon": -121.266495}, {"type": "node", "id": 58144397, "lat": 40.582059, "lon": -121.266473}, {"type": "node", "id": 58144398, "lat": 40.582009, "lon": -121.266458}, {"type": "node", "id": 58144400, "lat": 40.581906, "lon": -121.266448}, {"type": "node", "id": 58144402, "lat": 40.581483, "lon": -121.26648}, {"type": "node", "id": 58144404, "lat": 40.581248, "lon": -121.266511}, {"type": "node", "id": 58144406, "lat": 40.581018, "lon": -121.266553}, {"type": "node", "id": 58144408, "lat": 40.580637, "lon": -121.26664}, {"type": "node", "id": 58144411, "lat": 40.580406, "lon": -121.266664}, {"type": "node", "id": 58182124, "lat": 40.751862, "lon": -121.252033}, {"type": "node", "id": 58187068, "lat": 40.6792937, "lon": -121.1943499}, {"type": "node", "id": 58207573, "lat": 40.725456, "lon": -121.254914}, {"type": "node", "id": 58207634, "lat": 40.6470481, "lon": -121.1673342}, {"type": "node", "id": 58207641, "lat": 40.64329, "lon": -121.161266}, {"type": "node", "id": 58207653, "lat": 40.614828, "lon": -121.117005}, {"type": "node", "id": 58207729, "lat": 40.702519, "lon": -121.205235}, {"type": "node", "id": 58209731, "lat": 40.6493267, "lon": -121.1743891}, {"type": "node", "id": 58247691, "lat": 40.70594, "lon": -121.215723}, {"type": "node", "id": 58261706, "lat": 40.702575, "lon": -121.262105}, {"type": "node", "id": 58265404, "lat": 40.629301, "lon": -121.1412311}, {"type": "node", "id": 58280630, "lat": 40.644107, "lon": -121.162408}, {"type": "node", "id": 58280692, "lat": 40.635696, "lon": -121.150672}, {"type": "node", "id": 58287084, "lat": 40.731167, "lon": -121.253812}, {"type": "node", "id": 58300812, "lat": 40.645019, "lon": -121.217575}, {"type": "node", "id": 58304776, "lat": 40.7288, "lon": -121.255359}, {"type": "node", "id": 58305195, "lat": 40.650716, "lon": -121.3067373}, {"type": "node", "id": 58319084, "lat": 40.6279637, "lon": -121.1390893}, {"type": "node", "id": 58348320, "lat": 40.642789, "lon": -121.240726}, {"type": "node", "id": 58382852, "lat": 40.705942, "lon": -121.213816}, {"type": "node", "id": 58414597, "lat": 40.685229, "lon": -121.267291}, {"type": "node", "id": 58473443, "lat": 40.699712, "lon": -121.273021}, {"type": "node", "id": 58474081, "lat": 40.7322346, "lon": -121.2529954}, {"type": "node", "id": 58490682, "lat": 40.693407, "lon": -121.202089}, {"type": "node", "id": 58504312, "lat": 40.605594, "lon": -121.10738}, {"type": "node", "id": 58511994, "lat": 40.6438604, "lon": -121.2523758}, {"type": "node", "id": 58514128, "lat": 40.681433, "lon": -121.19441}, {"type": "node", "id": 58535852, "lat": 40.726314, "lon": -121.254271}, {"type": "node", "id": 58535853, "lat": 40.726222, "lon": -121.25427}, {"type": "node", "id": 58535855, "lat": 40.726134, "lon": -121.254307}, {"type": "node", "id": 58535861, "lat": 40.726096, "lon": -121.254336}, {"type": "node", "id": 58535862, "lat": 40.725702, "lon": -121.2547}, {"type": "node", "id": 58535867, "lat": 40.724833, "lon": -121.255503}, {"type": "node", "id": 58535869, "lat": 40.724604, "lon": -121.255711}, {"type": "node", "id": 58535872, "lat": 40.724189, "lon": -121.256158}, {"type": "node", "id": 58535874, "lat": 40.723761, "lon": -121.25664}, {"type": "node", "id": 58535875, "lat": 40.723383, "lon": -121.257094}, {"type": "node", "id": 58535879, "lat": 40.723269, "lon": -121.257189}, {"type": "node", "id": 58535880, "lat": 40.723202, "lon": -121.257236}, {"type": "node", "id": 58535883, "lat": 40.723103, "lon": -121.257292}, {"type": "node", "id": 58535884, "lat": 40.723, "lon": -121.257334}, {"type": "node", "id": 58535890, "lat": 40.722552, "lon": -121.25745}, {"type": "node", "id": 58535892, "lat": 40.722422, "lon": -121.257468}, {"type": "node", "id": 58535895, "lat": 40.722277, "lon": -121.257469}, {"type": "node", "id": 58535897, "lat": 40.721639, "lon": -121.257418}, {"type": "node", "id": 58535901, "lat": 40.721369, "lon": -121.257406}, {"type": "node", "id": 58535903, "lat": 40.72069, "lon": -121.257356}, {"type": "node", "id": 58535905, "lat": 40.719995, "lon": -121.257323}, {"type": "node", "id": 58535906, "lat": 40.719508, "lon": -121.257318}, {"type": "node", "id": 58535910, "lat": 40.718594, "lon": -121.257255}, {"type": "node", "id": 58535911, "lat": 40.718314, "lon": -121.257212}, {"type": "node", "id": 58535914, "lat": 40.718022, "lon": -121.257161}, {"type": "node", "id": 58535917, "lat": 40.717733, "lon": -121.257061}, {"type": "node", "id": 58535918, "lat": 40.716907, "lon": -121.256819}, {"type": "node", "id": 58535920, "lat": 40.716376, "lon": -121.256677}, {"type": "node", "id": 58535922, "lat": 40.716254, "lon": -121.256661}, {"type": "node", "id": 58535924, "lat": 40.715494, "lon": -121.256632}, {"type": "node", "id": 58535927, "lat": 40.715066, "lon": -121.256629}, {"type": "node", "id": 58535929, "lat": 40.714894, "lon": -121.256632}, {"type": "node", "id": 58535931, "lat": 40.71441, "lon": -121.256731}, {"type": "node", "id": 58535933, "lat": 40.714004, "lon": -121.256835}, {"type": "node", "id": 58535934, "lat": 40.713495, "lon": -121.257001}, {"type": "node", "id": 58535935, "lat": 40.713186, "lon": -121.257136}, {"type": "node", "id": 58535937, "lat": 40.712905, "lon": -121.257271}, {"type": "node", "id": 58535939, "lat": 40.712573, "lon": -121.257457}, {"type": "node", "id": 58535941, "lat": 40.711694, "lon": -121.257984}, {"type": "node", "id": 58535943, "lat": 40.711279, "lon": -121.258222}, {"type": "node", "id": 58535945, "lat": 40.710957, "lon": -121.258432}, {"type": "node", "id": 58535947, "lat": 40.709355, "lon": -121.259354}, {"type": "node", "id": 58535950, "lat": 40.709044, "lon": -121.259505}, {"type": "node", "id": 58535953, "lat": 40.708846, "lon": -121.25959}, {"type": "node", "id": 58535955, "lat": 40.708574, "lon": -121.259688}, {"type": "node", "id": 58535957, "lat": 40.708226, "lon": -121.25978}, {"type": "node", "id": 58535958, "lat": 40.707891, "lon": -121.259876}, {"type": "node", "id": 58535962, "lat": 40.707641, "lon": -121.259956}, {"type": "node", "id": 58535964, "lat": 40.706632, "lon": -121.260313}, {"type": "node", "id": 58535966, "lat": 40.705756, "lon": -121.260588}, {"type": "node", "id": 58535968, "lat": 40.705486, "lon": -121.260689}, {"type": "node", "id": 58535970, "lat": 40.704864, "lon": -121.26097}, {"type": "node", "id": 58535972, "lat": 40.703809, "lon": -121.261492}, {"type": "node", "id": 58535973, "lat": 40.703482, "lon": -121.261681}, {"type": "node", "id": 58535977, "lat": 40.703088, "lon": -121.26189}, {"type": "node", "id": 58535978, "lat": 40.702888, "lon": -121.261987}, {"type": "node", "id": 58535980, "lat": 40.702807, "lon": -121.262032}, {"type": "node", "id": 58535981, "lat": 40.702682, "lon": -121.262081}, {"type": "node", "id": 58535984, "lat": 40.702433, "lon": -121.26214}, {"type": "node", "id": 58535986, "lat": 40.702345, "lon": -121.262186}, {"type": "node", "id": 58535988, "lat": 40.702041, "lon": -121.262404}, {"type": "node", "id": 58535990, "lat": 40.701791, "lon": -121.262631}, {"type": "node", "id": 58535992, "lat": 40.701443, "lon": -121.263046}, {"type": "node", "id": 58535994, "lat": 40.701083, "lon": -121.263457}, {"type": "node", "id": 58535996, "lat": 40.700891, "lon": -121.263743}, {"type": "node", "id": 58535998, "lat": 40.700836, "lon": -121.263861}, {"type": "node", "id": 58536000, "lat": 40.700799, "lon": -121.263965}, {"type": "node", "id": 58536002, "lat": 40.700763, "lon": -121.264112}, {"type": "node", "id": 58536005, "lat": 40.700721, "lon": -121.264311}, {"type": "node", "id": 58536007, "lat": 40.700364, "lon": -121.265629}, {"type": "node", "id": 58536009, "lat": 40.700236, "lon": -121.266168}, {"type": "node", "id": 58536011, "lat": 40.700148, "lon": -121.266585}, {"type": "node", "id": 58536012, "lat": 40.700136, "lon": -121.266726}, {"type": "node", "id": 58536014, "lat": 40.700134, "lon": -121.266892}, {"type": "node", "id": 58536015, "lat": 40.700169, "lon": -121.267342}, {"type": "node", "id": 58536016, "lat": 40.700194, "lon": -121.267503}, {"type": "node", "id": 58536017, "lat": 40.700235, "lon": -121.267656}, {"type": "node", "id": 58536019, "lat": 40.700332, "lon": -121.267941}, {"type": "node", "id": 58536021, "lat": 40.700455, "lon": -121.268232}, {"type": "node", "id": 58536023, "lat": 40.700611, "lon": -121.268662}, {"type": "node", "id": 58536025, "lat": 40.700712, "lon": -121.268983}, {"type": "node", "id": 58536027, "lat": 40.70075, "lon": -121.269148}, {"type": "node", "id": 58536029, "lat": 40.700769, "lon": -121.269261}, {"type": "node", "id": 58536031, "lat": 40.700783, "lon": -121.269401}, {"type": "node", "id": 58536033, "lat": 40.700805, "lon": -121.269828}, {"type": "node", "id": 58536035, "lat": 40.700807, "lon": -121.269969}, {"type": "node", "id": 58536037, "lat": 40.700792, "lon": -121.27012}, {"type": "node", "id": 58536039, "lat": 40.700752, "lon": -121.270312}, {"type": "node", "id": 58536041, "lat": 40.700578, "lon": -121.270819}, {"type": "node", "id": 58536043, "lat": 40.700464, "lon": -121.27113}, {"type": "node", "id": 58536046, "lat": 40.700221, "lon": -121.271821}, {"type": "node", "id": 58536050, "lat": 40.700049, "lon": -121.272215}, {"type": "node", "id": 58536052, "lat": 40.699839, "lon": -121.272733}, {"type": "node", "id": 58536053, "lat": 40.699369, "lon": -121.273662}, {"type": "node", "id": 58536054, "lat": 40.699131, "lon": -121.274087}, {"type": "node", "id": 58536056, "lat": 40.69902, "lon": -121.274254}, {"type": "node", "id": 58536059, "lat": 40.698906, "lon": -121.274361}, {"type": "node", "id": 58536061, "lat": 40.698799, "lon": -121.274439}, {"type": "node", "id": 58536063, "lat": 40.698687, "lon": -121.274502}, {"type": "node", "id": 58536065, "lat": 40.698571, "lon": -121.27455}, {"type": "node", "id": 58536067, "lat": 40.698391, "lon": -121.27459}, {"type": "node", "id": 58536068, "lat": 40.698072, "lon": -121.274671}, {"type": "node", "id": 58536071, "lat": 40.697754, "lon": -121.274745}, {"type": "node", "id": 58536073, "lat": 40.697688, "lon": -121.274755}, {"type": "node", "id": 58536074, "lat": 40.697629, "lon": -121.27475}, {"type": "node", "id": 58536076, "lat": 40.697509, "lon": -121.274725}, {"type": "node", "id": 58536079, "lat": 40.697225, "lon": -121.274646}, {"type": "node", "id": 58536080, "lat": 40.697096, "lon": -121.274631}, {"type": "node", "id": 58536082, "lat": 40.696896, "lon": -121.274586}, {"type": "node", "id": 58536085, "lat": 40.696346, "lon": -121.274404}, {"type": "node", "id": 58536088, "lat": 40.695717, "lon": -121.274175}, {"type": "node", "id": 58536089, "lat": 40.695109, "lon": -121.273926}, {"type": "node", "id": 58536091, "lat": 40.694918, "lon": -121.273826}, {"type": "node", "id": 58536093, "lat": 40.694433, "lon": -121.273508}, {"type": "node", "id": 58536095, "lat": 40.694275, "lon": -121.273379}, {"type": "node", "id": 58536097, "lat": 40.694157, "lon": -121.273301}, {"type": "node", "id": 58536099, "lat": 40.694027, "lon": -121.273238}, {"type": "node", "id": 58536101, "lat": 40.693792, "lon": -121.273107}, {"type": "node", "id": 58536103, "lat": 40.693433, "lon": -121.272951}, {"type": "node", "id": 58536105, "lat": 40.692995, "lon": -121.272787}, {"type": "node", "id": 58536107, "lat": 40.692828, "lon": -121.272753}, {"type": "node", "id": 58536109, "lat": 40.692628, "lon": -121.272723}, {"type": "node", "id": 58536111, "lat": 40.692455, "lon": -121.272668}, {"type": "node", "id": 58536113, "lat": 40.69201, "lon": -121.272462}, {"type": "node", "id": 58536115, "lat": 40.691319, "lon": -121.2721}, {"type": "node", "id": 58536117, "lat": 40.690877, "lon": -121.271854}, {"type": "node", "id": 58536119, "lat": 40.690634, "lon": -121.271737}, {"type": "node", "id": 58536121, "lat": 40.690479, "lon": -121.271677}, {"type": "node", "id": 58536123, "lat": 40.689916, "lon": -121.271552}, {"type": "node", "id": 58536124, "lat": 40.689725, "lon": -121.271519}, {"type": "node", "id": 58536127, "lat": 40.689381, "lon": -121.2715}, {"type": "node", "id": 58536129, "lat": 40.689244, "lon": -121.27148}, {"type": "node", "id": 58536131, "lat": 40.689057, "lon": -121.271425}, {"type": "node", "id": 58536133, "lat": 40.688557, "lon": -121.27115}, {"type": "node", "id": 58536135, "lat": 40.688393, "lon": -121.271087}, {"type": "node", "id": 58536137, "lat": 40.688107, "lon": -121.270966}, {"type": "node", "id": 58536139, "lat": 40.687729, "lon": -121.270768}, {"type": "node", "id": 58536141, "lat": 40.68755, "lon": -121.270627}, {"type": "node", "id": 58536143, "lat": 40.687508, "lon": -121.270586}, {"type": "node", "id": 58536145, "lat": 40.68747, "lon": -121.27054}, {"type": "node", "id": 58536147, "lat": 40.687436, "lon": -121.270488}, {"type": "node", "id": 58536149, "lat": 40.687406, "lon": -121.270433}, {"type": "node", "id": 58536151, "lat": 40.687234, "lon": -121.270035}, {"type": "node", "id": 58536153, "lat": 40.687065, "lon": -121.269711}, {"type": "node", "id": 58536155, "lat": 40.686881, "lon": -121.269423}, {"type": "node", "id": 58536157, "lat": 40.686668, "lon": -121.269075}, {"type": "node", "id": 58536159, "lat": 40.686132, "lon": -121.26822}, {"type": "node", "id": 58536161, "lat": 40.686008, "lon": -121.268048}, {"type": "node", "id": 58536163, "lat": 40.685759, "lon": -121.267749}, {"type": "node", "id": 58536165, "lat": 40.685626, "lon": -121.267608}, {"type": "node", "id": 58536166, "lat": 40.685516, "lon": -121.267506}, {"type": "node", "id": 58536168, "lat": 40.685372, "lon": -121.267407}, {"type": "node", "id": 58536171, "lat": 40.684459, "lon": -121.26666}, {"type": "node", "id": 58536173, "lat": 40.683717, "lon": -121.266011}, {"type": "node", "id": 58536175, "lat": 40.683334, "lon": -121.265637}, {"type": "node", "id": 58536177, "lat": 40.683286, "lon": -121.265599}, {"type": "node", "id": 58536179, "lat": 40.683236, "lon": -121.265568}, {"type": "node", "id": 58536181, "lat": 40.683183, "lon": -121.265545}, {"type": "node", "id": 58536183, "lat": 40.683129, "lon": -121.265528}, {"type": "node", "id": 58536185, "lat": 40.682925, "lon": -121.265502}, {"type": "node", "id": 58536187, "lat": 40.682839, "lon": -121.265476}, {"type": "node", "id": 58536189, "lat": 40.682726, "lon": -121.265423}, {"type": "node", "id": 58536191, "lat": 40.682401, "lon": -121.265298}, {"type": "node", "id": 58536193, "lat": 40.682132, "lon": -121.265145}, {"type": "node", "id": 58536195, "lat": 40.681782, "lon": -121.264931}, {"type": "node", "id": 58536197, "lat": 40.681386, "lon": -121.264698}, {"type": "node", "id": 58536199, "lat": 40.681172, "lon": -121.264605}, {"type": "node", "id": 58536201, "lat": 40.6811, "lon": -121.26459}, {"type": "node", "id": 58536203, "lat": 40.681015, "lon": -121.264595}, {"type": "node", "id": 58536205, "lat": 40.680973, "lon": -121.264605}, {"type": "node", "id": 58536207, "lat": 40.680893, "lon": -121.264644}, {"type": "node", "id": 58536209, "lat": 40.680855, "lon": -121.264671}, {"type": "node", "id": 58536211, "lat": 40.68071, "lon": -121.264796}, {"type": "node", "id": 58536213, "lat": 40.680291, "lon": -121.26524}, {"type": "node", "id": 58536215, "lat": 40.679951, "lon": -121.265579}, {"type": "node", "id": 58536217, "lat": 40.6796, "lon": -121.265918}, {"type": "node", "id": 58536219, "lat": 40.679373, "lon": -121.266162}, {"type": "node", "id": 58536221, "lat": 40.679212, "lon": -121.26629}, {"type": "node", "id": 58536223, "lat": 40.679121, "lon": -121.266349}, {"type": "node", "id": 58536225, "lat": 40.678987, "lon": -121.266412}, {"type": "node", "id": 58536227, "lat": 40.678931, "lon": -121.266433}, {"type": "node", "id": 58536229, "lat": 40.678712, "lon": -121.266462}, {"type": "node", "id": 58536231, "lat": 40.678629, "lon": -121.266498}, {"type": "node", "id": 58536233, "lat": 40.67848, "lon": -121.266595}, {"type": "node", "id": 58536235, "lat": 40.678006, "lon": -121.266953}, {"type": "node", "id": 58536237, "lat": 40.677937, "lon": -121.267012}, {"type": "node", "id": 58536239, "lat": 40.677884, "lon": -121.267045}, {"type": "node", "id": 58536241, "lat": 40.677656, "lon": -121.267138}, {"type": "node", "id": 58536243, "lat": 40.677494, "lon": -121.267187}, {"type": "node", "id": 58536245, "lat": 40.67733, "lon": -121.267229}, {"type": "node", "id": 58536247, "lat": 40.677208, "lon": -121.267255}, {"type": "node", "id": 58536249, "lat": 40.677116, "lon": -121.267263}, {"type": "node", "id": 58536251, "lat": 40.677007, "lon": -121.267263}, {"type": "node", "id": 58536253, "lat": 40.676929, "lon": -121.267257}, {"type": "node", "id": 58536255, "lat": 40.676883, "lon": -121.267245}, {"type": "node", "id": 58536257, "lat": 40.676805, "lon": -121.267199}, {"type": "node", "id": 58536259, "lat": 40.676712, "lon": -121.267131}, {"type": "node", "id": 58536261, "lat": 40.676614, "lon": -121.267046}, {"type": "node", "id": 58536263, "lat": 40.676505, "lon": -121.266914}, {"type": "node", "id": 58536265, "lat": 40.676346, "lon": -121.26666}, {"type": "node", "id": 58536267, "lat": 40.676168, "lon": -121.266431}, {"type": "node", "id": 58536269, "lat": 40.676015, "lon": -121.266244}, {"type": "node", "id": 58536271, "lat": 40.675866, "lon": -121.266033}, {"type": "node", "id": 58536273, "lat": 40.675607, "lon": -121.265681}, {"type": "node", "id": 58536275, "lat": 40.675515, "lon": -121.26557}, {"type": "node", "id": 58536277, "lat": 40.675383, "lon": -121.265489}, {"type": "node", "id": 58536279, "lat": 40.675278, "lon": -121.265412}, {"type": "node", "id": 58536281, "lat": 40.675221, "lon": -121.26536}, {"type": "node", "id": 58536283, "lat": 40.674914, "lon": -121.265044}, {"type": "node", "id": 58536285, "lat": 40.674801, "lon": -121.264917}, {"type": "node", "id": 58536287, "lat": 40.674594, "lon": -121.264665}, {"type": "node", "id": 58536289, "lat": 40.674396, "lon": -121.264346}, {"type": "node", "id": 58536291, "lat": 40.674262, "lon": -121.264138}, {"type": "node", "id": 58536293, "lat": 40.674044, "lon": -121.263782}, {"type": "node", "id": 58536295, "lat": 40.67396, "lon": -121.26366}, {"type": "node", "id": 58536296, "lat": 40.673628, "lon": -121.263232}, {"type": "node", "id": 58536298, "lat": 40.673402, "lon": -121.262988}, {"type": "node", "id": 58536301, "lat": 40.673266, "lon": -121.262866}, {"type": "node", "id": 58536303, "lat": 40.673146, "lon": -121.262748}, {"type": "node", "id": 58536305, "lat": 40.672918, "lon": -121.262551}, {"type": "node", "id": 58536306, "lat": 40.672851, "lon": -121.2625}, {"type": "node", "id": 58536308, "lat": 40.672788, "lon": -121.262462}, {"type": "node", "id": 58536311, "lat": 40.672719, "lon": -121.26243}, {"type": "node", "id": 58536313, "lat": 40.672509, "lon": -121.262369}, {"type": "node", "id": 58536315, "lat": 40.672324, "lon": -121.262346}, {"type": "node", "id": 58536316, "lat": 40.671084, "lon": -121.262252}, {"type": "node", "id": 58536318, "lat": 40.67053, "lon": -121.262167}, {"type": "node", "id": 58536321, "lat": 40.670237, "lon": -121.262142}, {"type": "node", "id": 58536322, "lat": 40.669458, "lon": -121.262057}, {"type": "node", "id": 58536325, "lat": 40.669198, "lon": -121.262035}, {"type": "node", "id": 58536326, "lat": 40.668873, "lon": -121.262023}, {"type": "node", "id": 58536328, "lat": 40.667835, "lon": -121.262035}, {"type": "node", "id": 58536331, "lat": 40.667588, "lon": -121.262046}, {"type": "node", "id": 58536332, "lat": 40.667427, "lon": -121.262064}, {"type": "node", "id": 58536335, "lat": 40.667275, "lon": -121.262088}, {"type": "node", "id": 58536337, "lat": 40.667162, "lon": -121.262122}, {"type": "node", "id": 58536339, "lat": 40.666754, "lon": -121.262306}, {"type": "node", "id": 58536341, "lat": 40.666486, "lon": -121.262445}, {"type": "node", "id": 58536343, "lat": 40.66631, "lon": -121.262555}, {"type": "node", "id": 58536345, "lat": 40.666166, "lon": -121.262669}, {"type": "node", "id": 58536347, "lat": 40.665929, "lon": -121.262847}, {"type": "node", "id": 58536348, "lat": 40.665584, "lon": -121.263119}, {"type": "node", "id": 58536350, "lat": 40.665248, "lon": -121.263372}, {"type": "node", "id": 58536352, "lat": 40.664326, "lon": -121.263993}, {"type": "node", "id": 58536354, "lat": 40.663972, "lon": -121.264178}, {"type": "node", "id": 58536357, "lat": 40.663836, "lon": -121.264241}, {"type": "node", "id": 58536358, "lat": 40.663701, "lon": -121.264289}, {"type": "node", "id": 58536361, "lat": 40.663574, "lon": -121.264311}, {"type": "node", "id": 58536362, "lat": 40.663372, "lon": -121.264308}, {"type": "node", "id": 58536364, "lat": 40.663213, "lon": -121.264289}, {"type": "node", "id": 58536367, "lat": 40.663102, "lon": -121.264257}, {"type": "node", "id": 58536368, "lat": 40.662566, "lon": -121.264027}, {"type": "node", "id": 58536371, "lat": 40.662333, "lon": -121.263918}, {"type": "node", "id": 58536373, "lat": 40.661691, "lon": -121.263591}, {"type": "node", "id": 58536375, "lat": 40.661408, "lon": -121.263483}, {"type": "node", "id": 58536377, "lat": 40.661181, "lon": -121.263376}, {"type": "node", "id": 58536379, "lat": 40.661017, "lon": -121.263307}, {"type": "node", "id": 58536381, "lat": 40.660647, "lon": -121.263138}, {"type": "node", "id": 58536384, "lat": 40.659955, "lon": -121.262847}, {"type": "node", "id": 58536385, "lat": 40.65949, "lon": -121.262672}, {"type": "node", "id": 58536387, "lat": 40.659169, "lon": -121.262565}, {"type": "node", "id": 58536389, "lat": 40.658379, "lon": -121.262272}, {"type": "node", "id": 58536391, "lat": 40.658193, "lon": -121.262193}, {"type": "node", "id": 58536393, "lat": 40.657897, "lon": -121.26202}, {"type": "node", "id": 58536395, "lat": 40.657739, "lon": -121.261909}, {"type": "node", "id": 58536397, "lat": 40.657585, "lon": -121.261809}, {"type": "node", "id": 58536399, "lat": 40.657377, "lon": -121.261656}, {"type": "node", "id": 58536401, "lat": 40.657089, "lon": -121.261454}, {"type": "node", "id": 58536403, "lat": 40.656725, "lon": -121.261179}, {"type": "node", "id": 58536405, "lat": 40.65639, "lon": -121.260933}, {"type": "node", "id": 58536407, "lat": 40.655888, "lon": -121.260575}, {"type": "node", "id": 58536409, "lat": 40.655624, "lon": -121.260378}, {"type": "node", "id": 58536410, "lat": 40.655342, "lon": -121.26018}, {"type": "node", "id": 58536411, "lat": 40.65485, "lon": -121.25987}, {"type": "node", "id": 58536412, "lat": 40.65464, "lon": -121.259749}, {"type": "node", "id": 58536413, "lat": 40.654156, "lon": -121.259439}, {"type": "node", "id": 58536414, "lat": 40.653441, "lon": -121.258959}, {"type": "node", "id": 58536415, "lat": 40.652815, "lon": -121.258492}, {"type": "node", "id": 58536416, "lat": 40.652575, "lon": -121.258331}, {"type": "node", "id": 58536417, "lat": 40.651934, "lon": -121.257842}, {"type": "node", "id": 58536418, "lat": 40.651607, "lon": -121.257562}, {"type": "node", "id": 58536419, "lat": 40.651351, "lon": -121.25736}, {"type": "node", "id": 58536420, "lat": 40.651114, "lon": -121.257166}, {"type": "node", "id": 58536421, "lat": 40.650945, "lon": -121.257038}, {"type": "node", "id": 58536422, "lat": 40.650841, "lon": -121.25697}, {"type": "node", "id": 58536423, "lat": 40.65072, "lon": -121.256912}, {"type": "node", "id": 58536424, "lat": 40.650277, "lon": -121.256778}, {"type": "node", "id": 58536425, "lat": 40.650167, "lon": -121.256758}, {"type": "node", "id": 58536426, "lat": 40.649884, "lon": -121.256741}, {"type": "node", "id": 58536427, "lat": 40.649545, "lon": -121.256738}, {"type": "node", "id": 58536428, "lat": 40.649278, "lon": -121.256755}, {"type": "node", "id": 58536429, "lat": 40.648892, "lon": -121.256762}, {"type": "node", "id": 58536430, "lat": 40.648522, "lon": -121.256753}, {"type": "node", "id": 58536431, "lat": 40.648268, "lon": -121.256735}, {"type": "node", "id": 58536432, "lat": 40.647379, "lon": -121.256642}, {"type": "node", "id": 58536433, "lat": 40.647115, "lon": -121.256607}, {"type": "node", "id": 58536434, "lat": 40.646714, "lon": -121.256546}, {"type": "node", "id": 58536435, "lat": 40.646404, "lon": -121.256511}, {"type": "node", "id": 58536436, "lat": 40.645532, "lon": -121.256391}, {"type": "node", "id": 58536437, "lat": 40.645273, "lon": -121.256341}, {"type": "node", "id": 58536438, "lat": 40.644736, "lon": -121.256185}, {"type": "node", "id": 58536439, "lat": 40.64461, "lon": -121.256139}, {"type": "node", "id": 58536440, "lat": 40.644471, "lon": -121.256077}, {"type": "node", "id": 58536441, "lat": 40.644439, "lon": -121.25607}, {"type": "node", "id": 58536442, "lat": 40.644364, "lon": -121.25608}, {"type": "node", "id": 58536445, "lat": 40.6441774, "lon": -121.2561128}, {"type": "node", "id": 58548159, "lat": 40.75294, "lon": -121.252437}, {"type": "node", "id": 58548162, "lat": 40.75251, "lon": -121.252263}, {"type": "node", "id": 58548164, "lat": 40.752211, "lon": -121.252162}, {"type": "node", "id": 58548166, "lat": 40.751527, "lon": -121.251918}, {"type": "node", "id": 58548168, "lat": 40.751199, "lon": -121.251828}, {"type": "node", "id": 58548170, "lat": 40.750613, "lon": -121.251715}, {"type": "node", "id": 58548171, "lat": 40.750016, "lon": -121.251592}, {"type": "node", "id": 58548173, "lat": 40.749563, "lon": -121.251482}, {"type": "node", "id": 58548175, "lat": 40.748961, "lon": -121.25135}, {"type": "node", "id": 58548178, "lat": 40.748229, "lon": -121.25121}, {"type": "node", "id": 58548180, "lat": 40.74795, "lon": -121.251148}, {"type": "node", "id": 58548182, "lat": 40.747208, "lon": -121.251002}, {"type": "node", "id": 58548184, "lat": 40.746787, "lon": -121.250931}, {"type": "node", "id": 58548185, "lat": 40.746413, "lon": -121.250844}, {"type": "node", "id": 58548186, "lat": 40.745814, "lon": -121.250731}, {"type": "node", "id": 58548189, "lat": 40.745215, "lon": -121.250577}, {"type": "node", "id": 58548191, "lat": 40.744736, "lon": -121.250499}, {"type": "node", "id": 58548193, "lat": 40.743943, "lon": -121.250272}, {"type": "node", "id": 58548195, "lat": 40.743086, "lon": -121.250144}, {"type": "node", "id": 58548197, "lat": 40.742741, "lon": -121.250106}, {"type": "node", "id": 58548199, "lat": 40.742325, "lon": -121.25003}, {"type": "node", "id": 58548201, "lat": 40.742184, "lon": -121.249977}, {"type": "node", "id": 58548203, "lat": 40.742118, "lon": -121.24996}, {"type": "node", "id": 58548205, "lat": 40.741621, "lon": -121.249891}, {"type": "node", "id": 58548207, "lat": 40.741229, "lon": -121.249877}, {"type": "node", "id": 58548209, "lat": 40.740909, "lon": -121.24986}, {"type": "node", "id": 58548211, "lat": 40.740585, "lon": -121.249853}, {"type": "node", "id": 58548213, "lat": 40.740478, "lon": -121.249871}, {"type": "node", "id": 58548215, "lat": 40.739769, "lon": -121.249927}, {"type": "node", "id": 58548217, "lat": 40.739284, "lon": -121.249984}, {"type": "node", "id": 58548219, "lat": 40.738762, "lon": -121.250067}, {"type": "node", "id": 58548221, "lat": 40.738564, "lon": -121.250116}, {"type": "node", "id": 58548222, "lat": 40.738427, "lon": -121.250163}, {"type": "node", "id": 58548224, "lat": 40.738306, "lon": -121.250198}, {"type": "node", "id": 58548226, "lat": 40.737766, "lon": -121.250312}, {"type": "node", "id": 58548228, "lat": 40.737524, "lon": -121.25035}, {"type": "node", "id": 58548230, "lat": 40.737017, "lon": -121.250476}, {"type": "node", "id": 58548232, "lat": 40.736761, "lon": -121.250558}, {"type": "node", "id": 58548234, "lat": 40.7364, "lon": -121.250633}, {"type": "node", "id": 58548236, "lat": 40.736228, "lon": -121.250678}, {"type": "node", "id": 58548238, "lat": 40.735949, "lon": -121.250761}, {"type": "node", "id": 58548240, "lat": 40.735855, "lon": -121.250801}, {"type": "node", "id": 58548242, "lat": 40.735731, "lon": -121.250838}, {"type": "node", "id": 58548244, "lat": 40.735512, "lon": -121.250888}, {"type": "node", "id": 58548246, "lat": 40.735379, "lon": -121.250926}, {"type": "node", "id": 58548248, "lat": 40.735219, "lon": -121.250983}, {"type": "node", "id": 58548250, "lat": 40.734868, "lon": -121.251149}, {"type": "node", "id": 58548252, "lat": 40.734444, "lon": -121.251323}, {"type": "node", "id": 58548254, "lat": 40.734061, "lon": -121.251531}, {"type": "node", "id": 58548256, "lat": 40.733951, "lon": -121.251599}, {"type": "node", "id": 58548258, "lat": 40.733444, "lon": -121.251973}, {"type": "node", "id": 58548260, "lat": 40.732901, "lon": -121.252391}, {"type": "node", "id": 58548265, "lat": 40.730497, "lon": -121.254334}, {"type": "node", "id": 58548267, "lat": 40.729652, "lon": -121.255026}, {"type": "node", "id": 58548269, "lat": 40.7294, "lon": -121.255196}, {"type": "node", "id": 58548271, "lat": 40.729272, "lon": -121.255255}, {"type": "node", "id": 58548273, "lat": 40.729037, "lon": -121.255324}, {"type": "node", "id": 58548276, "lat": 40.728191, "lon": -121.255397}, {"type": "node", "id": 58548278, "lat": 40.728017, "lon": -121.255395}, {"type": "node", "id": 58548280, "lat": 40.727932, "lon": -121.255388}, {"type": "node", "id": 58548282, "lat": 40.727798, "lon": -121.255344}, {"type": "node", "id": 58548284, "lat": 40.727502, "lon": -121.255217}, {"type": "node", "id": 58548286, "lat": 40.727325, "lon": -121.25509}, {"type": "node", "id": 58548288, "lat": 40.727151, "lon": -121.254988}, {"type": "node", "id": 58548290, "lat": 40.72705, "lon": -121.254916}, {"type": "node", "id": 58548291, "lat": 40.726874, "lon": -121.254779}, {"type": "node", "id": 58548293, "lat": 40.726681, "lon": -121.254609}, {"type": "node", "id": 58548295, "lat": 40.72648, "lon": -121.25442}, {"type": "node", "id": 58548298, "lat": 40.724911, "lon": -121.253014}, {"type": "node", "id": 58548300, "lat": 40.724472, "lon": -121.25258}, {"type": "node", "id": 58548303, "lat": 40.72374, "lon": -121.251838}, {"type": "node", "id": 58548304, "lat": 40.723201, "lon": -121.251154}, {"type": "node", "id": 58548306, "lat": 40.722915, "lon": -121.250754}, {"type": "node", "id": 58548308, "lat": 40.722625, "lon": -121.250414}, {"type": "node", "id": 58548310, "lat": 40.721454, "lon": -121.249104}, {"type": "node", "id": 58548312, "lat": 40.721011, "lon": -121.248576}, {"type": "node", "id": 58548314, "lat": 40.720384, "lon": -121.247866}, {"type": "node", "id": 58548316, "lat": 40.72013, "lon": -121.247533}, {"type": "node", "id": 58548318, "lat": 40.71988, "lon": -121.247206}, {"type": "node", "id": 58548320, "lat": 40.719464, "lon": -121.246725}, {"type": "node", "id": 58548322, "lat": 40.719075, "lon": -121.246234}, {"type": "node", "id": 58548323, "lat": 40.718543, "lon": -121.24553}, {"type": "node", "id": 58548324, "lat": 40.717958, "lon": -121.244876}, {"type": "node", "id": 58548325, "lat": 40.717404, "lon": -121.244242}, {"type": "node", "id": 58548326, "lat": 40.716335, "lon": -121.242951}, {"type": "node", "id": 58548327, "lat": 40.715944, "lon": -121.242516}, {"type": "node", "id": 58548328, "lat": 40.714572, "lon": -121.240871}, {"type": "node", "id": 58548329, "lat": 40.714332, "lon": -121.240614}, {"type": "node", "id": 58548330, "lat": 40.714243, "lon": -121.240532}, {"type": "node", "id": 58548331, "lat": 40.714185, "lon": -121.240467}, {"type": "node", "id": 58548332, "lat": 40.714112, "lon": -121.240375}, {"type": "node", "id": 58548333, "lat": 40.713716, "lon": -121.239756}, {"type": "node", "id": 58548334, "lat": 40.713521, "lon": -121.239442}, {"type": "node", "id": 58548335, "lat": 40.713214, "lon": -121.23893}, {"type": "node", "id": 58548336, "lat": 40.712865, "lon": -121.238328}, {"type": "node", "id": 58548337, "lat": 40.712616, "lon": -121.237971}, {"type": "node", "id": 58548338, "lat": 40.712478, "lon": -121.237787}, {"type": "node", "id": 58548339, "lat": 40.712093, "lon": -121.237321}, {"type": "node", "id": 58548340, "lat": 40.712027, "lon": -121.237235}, {"type": "node", "id": 58548341, "lat": 40.711724, "lon": -121.236792}, {"type": "node", "id": 58548342, "lat": 40.711661, "lon": -121.236716}, {"type": "node", "id": 58548343, "lat": 40.711588, "lon": -121.236661}, {"type": "node", "id": 58548346, "lat": 40.711484, "lon": -121.23657}, {"type": "node", "id": 58548348, "lat": 40.711375, "lon": -121.236426}, {"type": "node", "id": 58548349, "lat": 40.711195, "lon": -121.236202}, {"type": "node", "id": 58548350, "lat": 40.71084, "lon": -121.235691}, {"type": "node", "id": 58548351, "lat": 40.71054, "lon": -121.235239}, {"type": "node", "id": 58548353, "lat": 40.71037, "lon": -121.235003}, {"type": "node", "id": 58548355, "lat": 40.710291, "lon": -121.234894}, {"type": "node", "id": 58548357, "lat": 40.710172, "lon": -121.234754}, {"type": "node", "id": 58548359, "lat": 40.709839, "lon": -121.234393}, {"type": "node", "id": 58548362, "lat": 40.709603, "lon": -121.234161}, {"type": "node", "id": 58548363, "lat": 40.709263, "lon": -121.233841}, {"type": "node", "id": 58548364, "lat": 40.709183, "lon": -121.233744}, {"type": "node", "id": 58548365, "lat": 40.709111, "lon": -121.233636}, {"type": "node", "id": 58548367, "lat": 40.709049, "lon": -121.233519}, {"type": "node", "id": 58548369, "lat": 40.708988, "lon": -121.233372}, {"type": "node", "id": 58548371, "lat": 40.708738, "lon": -121.232399}, {"type": "node", "id": 58548373, "lat": 40.708574, "lon": -121.231783}, {"type": "node", "id": 58548375, "lat": 40.708352, "lon": -121.230905}, {"type": "node", "id": 58548377, "lat": 40.708047, "lon": -121.229914}, {"type": "node", "id": 58548379, "lat": 40.707883, "lon": -121.229433}, {"type": "node", "id": 58548381, "lat": 40.707853, "lon": -121.229331}, {"type": "node", "id": 58548383, "lat": 40.70783, "lon": -121.229237}, {"type": "node", "id": 58548385, "lat": 40.707796, "lon": -121.228986}, {"type": "node", "id": 58548387, "lat": 40.707772, "lon": -121.228887}, {"type": "node", "id": 58548388, "lat": 40.707623, "lon": -121.228385}, {"type": "node", "id": 58548389, "lat": 40.707164, "lon": -121.227128}, {"type": "node", "id": 58548390, "lat": 40.706995, "lon": -121.226619}, {"type": "node", "id": 58548392, "lat": 40.706919, "lon": -121.226361}, {"type": "node", "id": 58548394, "lat": 40.706852, "lon": -121.226091}, {"type": "node", "id": 58548396, "lat": 40.706834, "lon": -121.225988}, {"type": "node", "id": 58548398, "lat": 40.706823, "lon": -121.225866}, {"type": "node", "id": 58548402, "lat": 40.706812, "lon": -121.225525}, {"type": "node", "id": 58548404, "lat": 40.7068, "lon": -121.22534}, {"type": "node", "id": 58548406, "lat": 40.706772, "lon": -121.225175}, {"type": "node", "id": 58548408, "lat": 40.706674, "lon": -121.224742}, {"type": "node", "id": 58548411, "lat": 40.706411, "lon": -121.223794}, {"type": "node", "id": 58548412, "lat": 40.7062, "lon": -121.223098}, {"type": "node", "id": 58548415, "lat": 40.706101, "lon": -121.222813}, {"type": "node", "id": 58548417, "lat": 40.706025, "lon": -121.222655}, {"type": "node", "id": 58548418, "lat": 40.705944, "lon": -121.222519}, {"type": "node", "id": 58548420, "lat": 40.705894, "lon": -121.222411}, {"type": "node", "id": 58548423, "lat": 40.705838, "lon": -121.22219}, {"type": "node", "id": 58548424, "lat": 40.705759, "lon": -121.22181}, {"type": "node", "id": 58548425, "lat": 40.705733, "lon": -121.221664}, {"type": "node", "id": 58548426, "lat": 40.705709, "lon": -121.221191}, {"type": "node", "id": 58548428, "lat": 40.705708, "lon": -121.220938}, {"type": "node", "id": 58548430, "lat": 40.705728, "lon": -121.220693}, {"type": "node", "id": 58548431, "lat": 40.705796, "lon": -121.22014}, {"type": "node", "id": 58548433, "lat": 40.705908, "lon": -121.218922}, {"type": "node", "id": 58548434, "lat": 40.705929, "lon": -121.218539}, {"type": "node", "id": 58548441, "lat": 40.70599, "lon": -121.2168761}, {"type": "node", "id": 58548446, "lat": 40.705928, "lon": -121.215291}, {"type": "node", "id": 58548447, "lat": 40.705943, "lon": -121.214069}, {"type": "node", "id": 58548450, "lat": 40.705966, "lon": -121.213314}, {"type": "node", "id": 58548452, "lat": 40.705976, "lon": -121.212844}, {"type": "node", "id": 58548454, "lat": 40.705967, "lon": -121.21259}, {"type": "node", "id": 58548456, "lat": 40.705945, "lon": -121.212314}, {"type": "node", "id": 58548460, "lat": 40.705903, "lon": -121.211939}, {"type": "node", "id": 58548463, "lat": 40.705889, "lon": -121.211767}, {"type": "node", "id": 58548465, "lat": 40.705865, "lon": -121.211375}, {"type": "node", "id": 58548467, "lat": 40.705786, "lon": -121.210775}, {"type": "node", "id": 58548469, "lat": 40.705727, "lon": -121.210169}, {"type": "node", "id": 58548471, "lat": 40.705645, "lon": -121.209486}, {"type": "node", "id": 58548473, "lat": 40.705575, "lon": -121.208753}, {"type": "node", "id": 58548475, "lat": 40.705544, "lon": -121.208496}, {"type": "node", "id": 58548476, "lat": 40.705436, "lon": -121.207885}, {"type": "node", "id": 58548477, "lat": 40.705375, "lon": -121.207626}, {"type": "node", "id": 58548478, "lat": 40.705298, "lon": -121.207412}, {"type": "node", "id": 58548480, "lat": 40.705225, "lon": -121.207231}, {"type": "node", "id": 58548482, "lat": 40.705112, "lon": -121.207009}, {"type": "node", "id": 58548484, "lat": 40.704987, "lon": -121.206815}, {"type": "node", "id": 58548485, "lat": 40.704815, "lon": -121.206594}, {"type": "node", "id": 58548487, "lat": 40.704474, "lon": -121.206241}, {"type": "node", "id": 58548490, "lat": 40.704252, "lon": -121.20605}, {"type": "node", "id": 58548492, "lat": 40.704134, "lon": -121.205975}, {"type": "node", "id": 58548494, "lat": 40.703968, "lon": -121.205879}, {"type": "node", "id": 58548495, "lat": 40.703578, "lon": -121.205713}, {"type": "node", "id": 58548496, "lat": 40.70199, "lon": -121.204999}, {"type": "node", "id": 58548498, "lat": 40.701835, "lon": -121.204934}, {"type": "node", "id": 58548500, "lat": 40.70172, "lon": -121.204893}, {"type": "node", "id": 58548503, "lat": 40.701576, "lon": -121.204857}, {"type": "node", "id": 58548504, "lat": 40.70141, "lon": -121.204825}, {"type": "node", "id": 58548507, "lat": 40.700994, "lon": -121.204761}, {"type": "node", "id": 58548508, "lat": 40.700382, "lon": -121.204685}, {"type": "node", "id": 58548510, "lat": 40.700002, "lon": -121.204623}, {"type": "node", "id": 58548513, "lat": 40.699266, "lon": -121.204549}, {"type": "node", "id": 58548514, "lat": 40.698981, "lon": -121.204508}, {"type": "node", "id": 58548515, "lat": 40.698817, "lon": -121.204477}, {"type": "node", "id": 58548516, "lat": 40.698722, "lon": -121.204451}, {"type": "node", "id": 58548518, "lat": 40.698592, "lon": -121.204398}, {"type": "node", "id": 58548520, "lat": 40.698371, "lon": -121.204319}, {"type": "node", "id": 58548522, "lat": 40.697588, "lon": -121.203954}, {"type": "node", "id": 58548525, "lat": 40.696943, "lon": -121.203631}, {"type": "node", "id": 58548526, "lat": 40.696679, "lon": -121.203483}, {"type": "node", "id": 58548528, "lat": 40.696467, "lon": -121.203394}, {"type": "node", "id": 58548530, "lat": 40.69639, "lon": -121.203367}, {"type": "node", "id": 58548532, "lat": 40.696326, "lon": -121.203357}, {"type": "node", "id": 58548533, "lat": 40.696187, "lon": -121.203345}, {"type": "node", "id": 58548535, "lat": 40.69591, "lon": -121.203311}, {"type": "node", "id": 58548537, "lat": 40.695422, "lon": -121.203264}, {"type": "node", "id": 58548539, "lat": 40.69497, "lon": -121.203196}, {"type": "node", "id": 58548541, "lat": 40.694922, "lon": -121.203181}, {"type": "node", "id": 58548542, "lat": 40.694823, "lon": -121.203137}, {"type": "node", "id": 58548544, "lat": 40.694582, "lon": -121.202962}, {"type": "node", "id": 58548548, "lat": 40.692514, "lon": -121.201494}, {"type": "node", "id": 58548550, "lat": 40.69193, "lon": -121.201087}, {"type": "node", "id": 58548551, "lat": 40.689991, "lon": -121.199668}, {"type": "node", "id": 58548552, "lat": 40.689443, "lon": -121.199184}, {"type": "node", "id": 58548553, "lat": 40.689037, "lon": -121.198857}, {"type": "node", "id": 58548556, "lat": 40.688802, "lon": -121.198676}, {"type": "node", "id": 58548558, "lat": 40.688359, "lon": -121.198412}, {"type": "node", "id": 58548559, "lat": 40.688187, "lon": -121.198323}, {"type": "node", "id": 58548561, "lat": 40.68786, "lon": -121.198122}, {"type": "node", "id": 58548564, "lat": 40.685729, "lon": -121.196664}, {"type": "node", "id": 58548565, "lat": 40.684935, "lon": -121.196103}, {"type": "node", "id": 58548566, "lat": 40.684191, "lon": -121.195563}, {"type": "node", "id": 58548568, "lat": 40.683898, "lon": -121.195364}, {"type": "node", "id": 58548569, "lat": 40.683686, "lon": -121.195207}, {"type": "node", "id": 58548571, "lat": 40.683505, "lon": -121.195115}, {"type": "node", "id": 58548573, "lat": 40.683211, "lon": -121.194953}, {"type": "node", "id": 58548575, "lat": 40.683015, "lon": -121.194865}, {"type": "node", "id": 58548577, "lat": 40.682678, "lon": -121.19473}, {"type": "node", "id": 58548578, "lat": 40.682426, "lon": -121.194643}, {"type": "node", "id": 58548580, "lat": 40.682155, "lon": -121.194562}, {"type": "node", "id": 58548583, "lat": 40.681782, "lon": -121.194469}, {"type": "node", "id": 58548585, "lat": 40.680442, "lon": -121.194336}, {"type": "node", "id": 58548869, "lat": 40.646789, "lon": -121.1666246}, {"type": "node", "id": 58558564, "lat": 40.7059985, "lon": -121.2173354, "tags": {"railway": "level_crossing"}}, {"type": "node", "id": 58558583, "lat": 40.7320318, "lon": -121.2531803, "tags": {"railway": "level_crossing"}}, {"type": "node", "id": 58566701, "lat": 40.642949, "lon": -121.1608045}, {"type": "node", "id": 58574564, "lat": 40.645991, "lon": -121.2794948}, {"type": "node", "id": 58575015, "lat": 40.587356, "lon": -121.294779}, {"type": "node", "id": 58616827, "lat": 40.611657, "lon": -121.112928}, {"type": "node", "id": 58646014, "lat": 40.648897, "lon": -121.300208}, {"type": "node", "id": 58656774, "lat": 40.646204, "lon": -121.216485}, {"type": "node", "id": 58719132, "lat": 40.594707, "lon": -121.096515}, {"type": "node", "id": 58719133, "lat": 40.595302, "lon": -121.097209}, {"type": "node", "id": 58719135, "lat": 40.595796, "lon": -121.097746}, {"type": "node", "id": 58719137, "lat": 40.59614, "lon": -121.098099}, {"type": "node", "id": 58719139, "lat": 40.596698, "lon": -121.098691}, {"type": "node", "id": 58719140, "lat": 40.597988, "lon": -121.100012}, {"type": "node", "id": 58719142, "lat": 40.599429, "lon": -121.101517}, {"type": "node", "id": 58719144, "lat": 40.600269, "lon": -121.102383}, {"type": "node", "id": 58719146, "lat": 40.601215, "lon": -121.103348}, {"type": "node", "id": 58719147, "lat": 40.601701, "lon": -121.103807}, {"type": "node", "id": 58719150, "lat": 40.606443, "lon": -121.10815}, {"type": "node", "id": 58719152, "lat": 40.606709, "lon": -121.1084}, {"type": "node", "id": 58719154, "lat": 40.606948, "lon": -121.108613}, {"type": "node", "id": 58719157, "lat": 40.608017, "lon": -121.109599}, {"type": "node", "id": 58719158, "lat": 40.608547, "lon": -121.110076}, {"type": "node", "id": 58719161, "lat": 40.608759, "lon": -121.110276}, {"type": "node", "id": 58719162, "lat": 40.609086, "lon": -121.110567}, {"type": "node", "id": 58719164, "lat": 40.609886, "lon": -121.111317}, {"type": "node", "id": 58719169, "lat": 40.610386, "lon": -121.111768}, {"type": "node", "id": 58719171, "lat": 40.610803, "lon": -121.112153}, {"type": "node", "id": 58719173, "lat": 40.612097, "lon": -121.113336}, {"type": "node", "id": 58719175, "lat": 40.612737, "lon": -121.113958}, {"type": "node", "id": 58719177, "lat": 40.61309, "lon": -121.114361}, {"type": "node", "id": 58719179, "lat": 40.613272, "lon": -121.114584}, {"type": "node", "id": 58719181, "lat": 40.613414, "lon": -121.114775}, {"type": "node", "id": 58719183, "lat": 40.614037, "lon": -121.115738}, {"type": "node", "id": 58719188, "lat": 40.615401, "lon": -121.117908}, {"type": "node", "id": 58719190, "lat": 40.615513, "lon": -121.118087}, {"type": "node", "id": 58719193, "lat": 40.615939, "lon": -121.118771}, {"type": "node", "id": 58719194, "lat": 40.616216, "lon": -121.119203}, {"type": "node", "id": 58719196, "lat": 40.617468, "lon": -121.121226}, {"type": "node", "id": 58719199, "lat": 40.617811, "lon": -121.121788}, {"type": "node", "id": 58719202, "lat": 40.618131, "lon": -121.122337}, {"type": "node", "id": 58719203, "lat": 40.618748, "lon": -121.123447}, {"type": "node", "id": 58719205, "lat": 40.619316, "lon": -121.124442}, {"type": "node", "id": 58719207, "lat": 40.619611, "lon": -121.124991}, {"type": "node", "id": 58719209, "lat": 40.620083, "lon": -121.125815}, {"type": "node", "id": 58719210, "lat": 40.620788, "lon": -121.127071}, {"type": "node", "id": 58719212, "lat": 40.621245, "lon": -121.127904}, {"type": "node", "id": 58719214, "lat": 40.621612, "lon": -121.128561}, {"type": "node", "id": 58719216, "lat": 40.622038, "lon": -121.129344}, {"type": "node", "id": 58719218, "lat": 40.623052, "lon": -121.131176}, {"type": "node", "id": 58719220, "lat": 40.623887, "lon": -121.132647}, {"type": "node", "id": 58719222, "lat": 40.624367, "lon": -121.13344}, {"type": "node", "id": 58719224, "lat": 40.625093, "lon": -121.134596}, {"type": "node", "id": 58719226, "lat": 40.62554, "lon": -121.135289}, {"type": "node", "id": 58719228, "lat": 40.625719, "lon": -121.135581}, {"type": "node", "id": 58719237, "lat": 40.6300433, "lon": -121.1424138}, {"type": "node", "id": 58719239, "lat": 40.631376, "lon": -121.144564}, {"type": "node", "id": 58719241, "lat": 40.631854, "lon": -121.145293}, {"type": "node", "id": 58719243, "lat": 40.632374, "lon": -121.146029}, {"type": "node", "id": 58719244, "lat": 40.633906, "lon": -121.148164}, {"type": "node", "id": 58719247, "lat": 40.634942, "lon": -121.149619}, {"type": "node", "id": 58719249, "lat": 40.635121, "lon": -121.149862}, {"type": "node", "id": 58719252, "lat": 40.638312, "lon": -121.154324}, {"type": "node", "id": 58719254, "lat": 40.638728, "lon": -121.154892}, {"type": "node", "id": 58719256, "lat": 40.641645, "lon": -121.158974}, {"type": "node", "id": 58719258, "lat": 40.642245, "lon": -121.159795}, {"type": "node", "id": 58719264, "lat": 40.643386, "lon": -121.161397}, {"type": "node", "id": 58719266, "lat": 40.643626, "lon": -121.161739}, {"type": "node", "id": 58719269, "lat": 40.644236, "lon": -121.162593}, {"type": "node", "id": 58719270, "lat": 40.64437, "lon": -121.162765}, {"type": "node", "id": 58719275, "lat": 40.6455726, "lon": -121.1644054}, {"type": "node", "id": 58719278, "lat": 40.6459274, "lon": -121.1649324}, {"type": "node", "id": 58719279, "lat": 40.646185, "lon": -121.1653562}, {"type": "node", "id": 58719281, "lat": 40.646364, "lon": -121.1656889}, {"type": "node", "id": 58719284, "lat": 40.6465115, "lon": -121.1659983}, {"type": "node", "id": 58719288, "lat": 40.6473731, "lon": -121.168301}, {"type": "node", "id": 58719290, "lat": 40.6478126, "lon": -121.1696964}, {"type": "node", "id": 58719292, "lat": 40.6484455, "lon": -121.1716701}, {"type": "node", "id": 58719294, "lat": 40.6489638, "lon": -121.17325}, {"type": "node", "id": 58719297, "lat": 40.649962, "lon": -121.176324}, {"type": "node", "id": 58719299, "lat": 40.6505097, "lon": -121.1780275}, {"type": "node", "id": 58719301, "lat": 40.6508571, "lon": -121.179301}, {"type": "node", "id": 58719304, "lat": 40.6511031, "lon": -121.1802733}, {"type": "node", "id": 58719305, "lat": 40.651335, "lon": -121.1813054}, {"type": "node", "id": 58719308, "lat": 40.6515229, "lon": -121.1822223}, {"type": "node", "id": 58719311, "lat": 40.6516696, "lon": -121.1830229}, {"type": "node", "id": 58719313, "lat": 40.6517924, "lon": -121.1837626}, {"type": "node", "id": 58719315, "lat": 40.6518954, "lon": -121.1844666}, {"type": "node", "id": 58719317, "lat": 40.6519809, "lon": -121.1851021}, {"type": "node", "id": 58719319, "lat": 40.6520969, "lon": -121.1860259}, {"type": "node", "id": 58719320, "lat": 40.6522502, "lon": -121.1872469}, {"type": "node", "id": 58719322, "lat": 40.652453, "lon": -121.1888123}, {"type": "node", "id": 58719323, "lat": 40.652959, "lon": -121.192977}, {"type": "node", "id": 58719324, "lat": 40.65304, "lon": -121.193563}, {"type": "node", "id": 58719325, "lat": 40.653341, "lon": -121.195933}, {"type": "node", "id": 58719326, "lat": 40.653512, "lon": -121.197215}, {"type": "node", "id": 58719327, "lat": 40.653588, "lon": -121.197698}, {"type": "node", "id": 58719328, "lat": 40.653651, "lon": -121.198056}, {"type": "node", "id": 58719329, "lat": 40.653742, "lon": -121.198445}, {"type": "node", "id": 58719330, "lat": 40.653877, "lon": -121.198945}, {"type": "node", "id": 58719331, "lat": 40.6544187, "lon": -121.2008444}, {"type": "node", "id": 58719332, "lat": 40.6545449, "lon": -121.2012841}, {"type": "node", "id": 58719333, "lat": 40.6546179, "lon": -121.2015852}, {"type": "node", "id": 58719334, "lat": 40.654658, "lon": -121.2018}, {"type": "node", "id": 58719335, "lat": 40.654688, "lon": -121.202031}, {"type": "node", "id": 58719336, "lat": 40.654709, "lon": -121.202287}, {"type": "node", "id": 58719337, "lat": 40.654728, "lon": -121.202634}, {"type": "node", "id": 58719338, "lat": 40.654729, "lon": -121.202906}, {"type": "node", "id": 58719339, "lat": 40.654725, "lon": -121.203116}, {"type": "node", "id": 58719340, "lat": 40.654683, "lon": -121.203483}, {"type": "node", "id": 58719341, "lat": 40.654631, "lon": -121.203829}, {"type": "node", "id": 58719342, "lat": 40.654591, "lon": -121.204021}, {"type": "node", "id": 58719343, "lat": 40.654506, "lon": -121.204352}, {"type": "node", "id": 58719344, "lat": 40.6543554, "lon": -121.2048269}, {"type": "node", "id": 58719345, "lat": 40.6541487, "lon": -121.2053667}, {"type": "node", "id": 58719348, "lat": 40.6538041, "lon": -121.2062178}, {"type": "node", "id": 58719349, "lat": 40.652885, "lon": -121.208532}, {"type": "node", "id": 58719350, "lat": 40.6526511, "lon": -121.2091378}, {"type": "node", "id": 58719352, "lat": 40.652393, "lon": -121.209788}, {"type": "node", "id": 58719354, "lat": 40.6521333, "lon": -121.2104488}, {"type": "node", "id": 58719355, "lat": 40.651581, "lon": -121.211602}, {"type": "node", "id": 58719357, "lat": 40.65146, "lon": -121.211814}, {"type": "node", "id": 58719359, "lat": 40.651093, "lon": -121.212388}, {"type": "node", "id": 58719361, "lat": 40.650807, "lon": -121.212779}, {"type": "node", "id": 58719363, "lat": 40.650589, "lon": -121.213051}, {"type": "node", "id": 58719365, "lat": 40.650326, "lon": -121.213351}, {"type": "node", "id": 58719368, "lat": 40.650182, "lon": -121.213498}, {"type": "node", "id": 58719369, "lat": 40.64994, "lon": -121.213731}, {"type": "node", "id": 58719371, "lat": 40.64969, "lon": -121.213946}, {"type": "node", "id": 58719373, "lat": 40.649326, "lon": -121.214229}, {"type": "node", "id": 58719376, "lat": 40.647224, "lon": -121.215743}, {"type": "node", "id": 58719378, "lat": 40.646447, "lon": -121.216317}, {"type": "node", "id": 58719380, "lat": 40.645787, "lon": -121.21681}, {"type": "node", "id": 58719382, "lat": 40.645528, "lon": -121.217037}, {"type": "node", "id": 58719383, "lat": 40.645276, "lon": -121.21729}, {"type": "node", "id": 58719384, "lat": 40.644993, "lon": -121.217606}, {"type": "node", "id": 58719387, "lat": 40.644938, "lon": -121.217687}, {"type": "node", "id": 58719388, "lat": 40.644752, "lon": -121.217942}, {"type": "node", "id": 58719390, "lat": 40.644419, "lon": -121.218446}, {"type": "node", "id": 58719392, "lat": 40.644317, "lon": -121.218624}, {"type": "node", "id": 58719393, "lat": 40.644128, "lon": -121.218986}, {"type": "node", "id": 58719394, "lat": 40.643875, "lon": -121.219544}, {"type": "node", "id": 58719395, "lat": 40.643611, "lon": -121.220163}, {"type": "node", "id": 58719396, "lat": 40.643119, "lon": -121.22134}, {"type": "node", "id": 58719397, "lat": 40.64288, "lon": -121.221928}, {"type": "node", "id": 58719398, "lat": 40.642696, "lon": -121.222354}, {"type": "node", "id": 58719400, "lat": 40.64255, "lon": -121.222715}, {"type": "node", "id": 58719402, "lat": 40.642332, "lon": -121.223207}, {"type": "node", "id": 58719404, "lat": 40.641772, "lon": -121.224543}, {"type": "node", "id": 58719406, "lat": 40.641658, "lon": -121.224802}, {"type": "node", "id": 58719410, "lat": 40.641364, "lon": -121.225515}, {"type": "node", "id": 58719412, "lat": 40.6412233, "lon": -121.2259543}, {"type": "node", "id": 58719414, "lat": 40.6411283, "lon": -121.2263877}, {"type": "node", "id": 58719416, "lat": 40.6410544, "lon": -121.2267642}, {"type": "node", "id": 58719417, "lat": 40.6410141, "lon": -121.2271716}, {"type": "node", "id": 58719419, "lat": 40.640994, "lon": -121.2274736}, {"type": "node", "id": 58719422, "lat": 40.6409745, "lon": -121.2278172}, {"type": "node", "id": 58719424, "lat": 40.6409785, "lon": -121.2282541}, {"type": "node", "id": 58719426, "lat": 40.641013, "lon": -121.2286677}, {"type": "node", "id": 58719428, "lat": 40.6410829, "lon": -121.2291949}, {"type": "node", "id": 58719430, "lat": 40.64129, "lon": -121.230576}, {"type": "node", "id": 58719432, "lat": 40.641521, "lon": -121.232129}, {"type": "node", "id": 58719434, "lat": 40.641705, "lon": -121.233442}, {"type": "node", "id": 58719436, "lat": 40.641847, "lon": -121.234347}, {"type": "node", "id": 58719438, "lat": 40.641888, "lon": -121.234652}, {"type": "node", "id": 58719440, "lat": 40.641989, "lon": -121.235318}, {"type": "node", "id": 58719442, "lat": 40.642059, "lon": -121.235811}, {"type": "node", "id": 58719444, "lat": 40.642241, "lon": -121.237006}, {"type": "node", "id": 58719446, "lat": 40.642327, "lon": -121.237604}, {"type": "node", "id": 58719448, "lat": 40.642436, "lon": -121.238307}, {"type": "node", "id": 58719452, "lat": 40.643096, "lon": -121.242957}, {"type": "node", "id": 58719454, "lat": 40.643155, "lon": -121.243482}, {"type": "node", "id": 58719455, "lat": 40.643273, "lon": -121.24468}, {"type": "node", "id": 58719458, "lat": 40.6434311, "lon": -121.2467991}, {"type": "node", "id": 58719463, "lat": 40.6437104, "lon": -121.2504057}, {"type": "node", "id": 58719469, "lat": 40.6444853, "lon": -121.2602782}, {"type": "node", "id": 58719472, "lat": 40.6445742, "lon": -121.2614171}, {"type": "node", "id": 58719474, "lat": 40.6447075, "lon": -121.2630534}, {"type": "node", "id": 58719475, "lat": 40.6448792, "lon": -121.265309}, {"type": "node", "id": 58719477, "lat": 40.6450001, "lon": -121.2668423}, {"type": "node", "id": 58719480, "lat": 40.6451093, "lon": -121.2681385}, {"type": "node", "id": 58719483, "lat": 40.6452176, "lon": -121.2695863}, {"type": "node", "id": 58719487, "lat": 40.6454798, "lon": -121.2728773}, {"type": "node", "id": 58719493, "lat": 40.6456372, "lon": -121.2748986}, {"type": "node", "id": 58719495, "lat": 40.6458814, "lon": -121.2780169}, {"type": "node", "id": 58719502, "lat": 40.646138, "lon": -121.281712}, {"type": "node", "id": 58719504, "lat": 40.646166, "lon": -121.282127}, {"type": "node", "id": 58719506, "lat": 40.646309, "lon": -121.283922}, {"type": "node", "id": 58719513, "lat": 40.6465132, "lon": -121.2861228}, {"type": "node", "id": 58719521, "lat": 40.646865, "lon": -121.291065}, {"type": "node", "id": 58719523, "lat": 40.646924, "lon": -121.291913}, {"type": "node", "id": 58719525, "lat": 40.647008, "lon": -121.292737}, {"type": "node", "id": 58719527, "lat": 40.647029, "lon": -121.2929}, {"type": "node", "id": 58719529, "lat": 40.647105, "lon": -121.293415}, {"type": "node", "id": 58719530, "lat": 40.647149, "lon": -121.293673}, {"type": "node", "id": 58719533, "lat": 40.647205, "lon": -121.293967}, {"type": "node", "id": 58719536, "lat": 40.647286, "lon": -121.294362}, {"type": "node", "id": 58719537, "lat": 40.647431, "lon": -121.294951}, {"type": "node", "id": 58719538, "lat": 40.647601, "lon": -121.295584}, {"type": "node", "id": 58719539, "lat": 40.647971, "lon": -121.296916}, {"type": "node", "id": 58719540, "lat": 40.648306, "lon": -121.298096}, {"type": "node", "id": 58719541, "lat": 40.649344, "lon": -121.301807}, {"type": "node", "id": 58719542, "lat": 40.649667, "lon": -121.302931}, {"type": "node", "id": 58719543, "lat": 40.651319, "lon": -121.308895}, {"type": "node", "id": 58719545, "lat": 40.651694, "lon": -121.310201}, {"type": "node", "id": 58719547, "lat": 40.653374, "lon": -121.316223}, {"type": "node", "id": 58719549, "lat": 40.653684, "lon": -121.31735}, {"type": "node", "id": 58719551, "lat": 40.654743, "lon": -121.321154}, {"type": "node", "id": 58719553, "lat": 40.654957, "lon": -121.32191}, {"type": "node", "id": 90097154, "lat": 40.3902233, "lon": -121.3085266}, {"type": "node", "id": 90106407, "lat": 40.4336256, "lon": -121.3491048}, {"type": "node", "id": 90219602, "lat": 40.406035, "lon": -121.315078}, {"type": "node", "id": 2925406570, "lat": 40.3882763, "lon": -121.3105094}, {"type": "node", "id": 2925406571, "lat": 40.3882657, "lon": -121.310693}, {"type": "node", "id": 2925406572, "lat": 40.3882988, "lon": -121.3104048}, {"type": "node", "id": 2925406573, "lat": 40.3883519, "lon": -121.3102546}, {"type": "node", "id": 2925406575, "lat": 40.3883534, "lon": -121.3109921}, {"type": "node", "id": 2925406576, "lat": 40.3884377, "lon": -121.3100964}, {"type": "node", "id": 2925406578, "lat": 40.3886134, "lon": -121.3098255}, {"type": "node", "id": 2925406584, "lat": 40.3890552, "lon": -121.3091204}, {"type": "node", "id": 2925406585, "lat": 40.3893789, "lon": -121.3086131}, {"type": "node", "id": 2925406586, "lat": 40.3895168, "lon": -121.3084184}, {"type": "node", "id": 2925406587, "lat": 40.389617, "lon": -121.3083608}, {"type": "node", "id": 2925406588, "lat": 40.3897256, "lon": -121.3083471}, {"type": "node", "id": 2925406589, "lat": 40.3898467, "lon": -121.30838}, {"type": "node", "id": 2925406590, "lat": 40.3900866, "lon": -121.3084732}, {"type": "node", "id": 2925406592, "lat": 40.3909638, "lon": -121.3087584}, {"type": "node", "id": 2925406593, "lat": 40.3915109, "lon": -121.3089257}, {"type": "node", "id": 2925406594, "lat": 40.3923003, "lon": -121.3091752}, {"type": "node", "id": 2925406595, "lat": 40.3930396, "lon": -121.3093946}, {"type": "node", "id": 2925406596, "lat": 40.3932882, "lon": -121.309485}, {"type": "node", "id": 2925406597, "lat": 40.3934657, "lon": -121.3095673}, {"type": "node", "id": 2925406598, "lat": 40.3937497, "lon": -121.3097236}, {"type": "node", "id": 2925406599, "lat": 40.3945788, "lon": -121.310198}, {"type": "node", "id": 2925406600, "lat": 40.394963, "lon": -121.3104365}, {"type": "node", "id": 2925407001, "lat": 40.3956, "lon": -121.3108149}, {"type": "node", "id": 2925407002, "lat": 40.3966253, "lon": -121.3114401}, {"type": "node", "id": 2925407003, "lat": 40.3971599, "lon": -121.3117555}, {"type": "node", "id": 2925407004, "lat": 40.3975608, "lon": -121.3119803}, {"type": "node", "id": 2925407005, "lat": 40.3979848, "lon": -121.3122134}, {"type": "node", "id": 2925407006, "lat": 40.3982896, "lon": -121.3123889}, {"type": "node", "id": 2925407007, "lat": 40.3984546, "lon": -121.3124848}, {"type": "node", "id": 2925407008, "lat": 40.3985632, "lon": -121.3126055}, {"type": "node", "id": 2925407009, "lat": 40.3986572, "lon": -121.3127344}, {"type": "node", "id": 2925407010, "lat": 40.398747, "lon": -121.3128413}, {"type": "node", "id": 2925407011, "lat": 40.3988263, "lon": -121.3129071}, {"type": "node", "id": 2925407012, "lat": 40.3989829, "lon": -121.3130141}, {"type": "node", "id": 2925407013, "lat": 40.3998036, "lon": -121.3134884}, {"type": "node", "id": 2925407014, "lat": 40.4005073, "lon": -121.3139162}, {"type": "node", "id": 2925407015, "lat": 40.4009249, "lon": -121.314163}, {"type": "node", "id": 2925407016, "lat": 40.4011776, "lon": -121.3142836}, {"type": "node", "id": 2925407017, "lat": 40.4013697, "lon": -121.3143741}, {"type": "node", "id": 2925407018, "lat": 40.4015054, "lon": -121.3143906}, {"type": "node", "id": 2925407019, "lat": 40.4016829, "lon": -121.3143851}, {"type": "node", "id": 2925407020, "lat": 40.4018479, "lon": -121.3143165}, {"type": "node", "id": 2925407021, "lat": 40.4020254, "lon": -121.314226}, {"type": "node", "id": 2925407022, "lat": 40.4022655, "lon": -121.3140588}, {"type": "node", "id": 2925407023, "lat": 40.4026518, "lon": -121.3137818}, {"type": "node", "id": 2925407024, "lat": 40.4029817, "lon": -121.3135241}, {"type": "node", "id": 2925407025, "lat": 40.4031404, "lon": -121.3134144}, {"type": "node", "id": 2925407026, "lat": 40.4033033, "lon": -121.313376}, {"type": "node", "id": 2925407027, "lat": 40.4034014, "lon": -121.3133979}, {"type": "node", "id": 2925407028, "lat": 40.4034891, "lon": -121.3134254}, {"type": "node", "id": 2925407029, "lat": 40.4035893, "lon": -121.3134747}, {"type": "node", "id": 2925407030, "lat": 40.4037334, "lon": -121.313557}, {"type": "node", "id": 2925407031, "lat": 40.4044225, "lon": -121.3140012}, {"type": "node", "id": 2925407032, "lat": 40.4049152, "lon": -121.3143193}, {"type": "node", "id": 2925407033, "lat": 40.4053036, "lon": -121.3145688}, {"type": "node", "id": 2925407034, "lat": 40.4066211, "lon": -121.3154462}, {"type": "node", "id": 2925407035, "lat": 40.4068362, "lon": -121.3155806}, {"type": "node", "id": 2925407036, "lat": 40.4070867, "lon": -121.3157698}, {"type": "node", "id": 2925407037, "lat": 40.4072579, "lon": -121.3159234}, {"type": "node", "id": 2925407038, "lat": 40.4074417, "lon": -121.3161098}, {"type": "node", "id": 2925407039, "lat": 40.407757, "lon": -121.3163511}, {"type": "node", "id": 2925407040, "lat": 40.4083562, "lon": -121.3168365}, {"type": "node", "id": 2925407041, "lat": 40.4087508, "lon": -121.3171326}, {"type": "node", "id": 2925407042, "lat": 40.4089763, "lon": -121.3173136}, {"type": "node", "id": 2925407043, "lat": 40.4090911, "lon": -121.3173903}, {"type": "node", "id": 2925407044, "lat": 40.4091788, "lon": -121.3174918}, {"type": "node", "id": 2925407045, "lat": 40.4092853, "lon": -121.317607}, {"type": "node", "id": 2925407046, "lat": 40.4093584, "lon": -121.3177687}, {"type": "node", "id": 2925407047, "lat": 40.4095045, "lon": -121.3180731}, {"type": "node", "id": 2925407048, "lat": 40.409659, "lon": -121.3183693}, {"type": "node", "id": 2925407049, "lat": 40.4099117, "lon": -121.3188107}, {"type": "node", "id": 2925407050, "lat": 40.4101747, "lon": -121.3191891}, {"type": "node", "id": 2925407051, "lat": 40.4103981, "lon": -121.3194606}, {"type": "node", "id": 2925407052, "lat": 40.4105318, "lon": -121.3196004}, {"type": "node", "id": 2925407053, "lat": 40.4108575, "lon": -121.3198253}, {"type": "node", "id": 2925407054, "lat": 40.4114734, "lon": -121.3202421}, {"type": "node", "id": 2925407055, "lat": 40.4117949, "lon": -121.3204861}, {"type": "node", "id": 2925407056, "lat": 40.4124943, "lon": -121.3210455}, {"type": "node", "id": 2925407057, "lat": 40.4128158, "lon": -121.3213169}, {"type": "node", "id": 2925407059, "lat": 40.4130142, "lon": -121.3214897}, {"type": "node", "id": 2925407060, "lat": 40.4132856, "lon": -121.3216762}, {"type": "node", "id": 2925407061, "lat": 40.4138576, "lon": -121.3220902}, {"type": "node", "id": 2925407062, "lat": 40.4142626, "lon": -121.3223562}, {"type": "node", "id": 2925407063, "lat": 40.4143628, "lon": -121.3224302}, {"type": "node", "id": 2925407064, "lat": 40.4144944, "lon": -121.3225042}, {"type": "node", "id": 2925407065, "lat": 40.4146885, "lon": -121.322592}, {"type": "node", "id": 2925407066, "lat": 40.4149036, "lon": -121.3227017}, {"type": "node", "id": 2925407067, "lat": 40.4153733, "lon": -121.3229183}, {"type": "node", "id": 2925407068, "lat": 40.4155006, "lon": -121.3229814}, {"type": "node", "id": 2925407069, "lat": 40.4156238, "lon": -121.3230773}, {"type": "node", "id": 2925407070, "lat": 40.4159557, "lon": -121.3233625}, {"type": "node", "id": 2925407071, "lat": 40.4163253, "lon": -121.3236641}, {"type": "node", "id": 2925407072, "lat": 40.4165904, "lon": -121.3238643}, {"type": "node", "id": 2925407073, "lat": 40.4167491, "lon": -121.3240069}, {"type": "node", "id": 2925407074, "lat": 40.4169119, "lon": -121.324229}, {"type": "node", "id": 2925407075, "lat": 40.4171729, "lon": -121.3246266}, {"type": "node", "id": 2925407076, "lat": 40.4174797, "lon": -121.3251558}, {"type": "node", "id": 2925407077, "lat": 40.4178513, "lon": -121.3258111}, {"type": "node", "id": 2925407078, "lat": 40.4181039, "lon": -121.3262499}, {"type": "node", "id": 2925407079, "lat": 40.4183377, "lon": -121.3267544}, {"type": "node", "id": 2925407080, "lat": 40.4185361, "lon": -121.3272425}, {"type": "node", "id": 2925407081, "lat": 40.4188033, "lon": -121.3279445}, {"type": "node", "id": 2925407082, "lat": 40.4190788, "lon": -121.3285833}, {"type": "node", "id": 2925407083, "lat": 40.4192396, "lon": -121.3290029}, {"type": "node", "id": 2925407084, "lat": 40.4193669, "lon": -121.3293264}, {"type": "node", "id": 2925407085, "lat": 40.419488, "lon": -121.329554}, {"type": "node", "id": 2925407086, "lat": 40.4195757, "lon": -121.329661}, {"type": "node", "id": 2925407087, "lat": 40.419703, "lon": -121.3298118}, {"type": "node", "id": 2925407088, "lat": 40.4199827, "lon": -121.3301792}, {"type": "node", "id": 2925407089, "lat": 40.4200579, "lon": -121.3302395}, {"type": "node", "id": 2925407090, "lat": 40.4201268, "lon": -121.3302834}, {"type": "node", "id": 2925407091, "lat": 40.4201873, "lon": -121.3302889}, {"type": "node", "id": 2925407092, "lat": 40.420252, "lon": -121.3302807}, {"type": "node", "id": 2925407093, "lat": 40.4203898, "lon": -121.330256}, {"type": "node", "id": 2925407094, "lat": 40.4206842, "lon": -121.3301737}, {"type": "node", "id": 2925407095, "lat": 40.4207593, "lon": -121.3301737}, {"type": "node", "id": 2925407096, "lat": 40.4208115, "lon": -121.3302176}, {"type": "node", "id": 2925407097, "lat": 40.4208616, "lon": -121.3302642}, {"type": "node", "id": 2925407098, "lat": 40.4211685, "lon": -121.3306179}, {"type": "node", "id": 2925407099, "lat": 40.4214315, "lon": -121.3309333}, {"type": "node", "id": 2925407100, "lat": 40.4216841, "lon": -121.3313172}, {"type": "node", "id": 2925407101, "lat": 40.4217676, "lon": -121.3314323}, {"type": "node", "id": 2925407102, "lat": 40.4218594, "lon": -121.3315914}, {"type": "node", "id": 2925407103, "lat": 40.4220452, "lon": -121.3318025}, {"type": "node", "id": 2925407104, "lat": 40.4221851, "lon": -121.3319341}, {"type": "node", "id": 2925407105, "lat": 40.4222498, "lon": -121.3320246}, {"type": "node", "id": 2925407106, "lat": 40.422327, "lon": -121.3321562}, {"type": "node", "id": 2925407107, "lat": 40.4224147, "lon": -121.3323811}, {"type": "node", "id": 2925407108, "lat": 40.4224878, "lon": -121.3326087}, {"type": "node", "id": 2925407109, "lat": 40.4225671, "lon": -121.3327375}, {"type": "node", "id": 2925407110, "lat": 40.4226339, "lon": -121.332828}, {"type": "node", "id": 2925407111, "lat": 40.4228343, "lon": -121.3330309}, {"type": "node", "id": 2925407112, "lat": 40.4230054, "lon": -121.333168}, {"type": "node", "id": 2925407113, "lat": 40.423091, "lon": -121.333264}, {"type": "node", "id": 2925407114, "lat": 40.4232476, "lon": -121.3334806}, {"type": "node", "id": 2925407115, "lat": 40.4233499, "lon": -121.3336616}, {"type": "node", "id": 2925407116, "lat": 40.4235106, "lon": -121.3339111}, {"type": "node", "id": 2925407117, "lat": 40.4236797, "lon": -121.33421}, {"type": "node", "id": 2925407118, "lat": 40.4237903, "lon": -121.3343032}, {"type": "node", "id": 2925407119, "lat": 40.4238968, "lon": -121.3343526}, {"type": "node", "id": 2925407120, "lat": 40.4240993, "lon": -121.3344047}, {"type": "node", "id": 2925407121, "lat": 40.4244061, "lon": -121.334476}, {"type": "node", "id": 2925407122, "lat": 40.4247777, "lon": -121.3345994}, {"type": "node", "id": 2925407123, "lat": 40.4249843, "lon": -121.3346323}, {"type": "node", "id": 2925407124, "lat": 40.4252619, "lon": -121.3346734}, {"type": "node", "id": 2925407125, "lat": 40.4253726, "lon": -121.3346871}, {"type": "node", "id": 2925407126, "lat": 40.4254707, "lon": -121.334731}, {"type": "node", "id": 2925407127, "lat": 40.425861, "lon": -121.3350518}, {"type": "node", "id": 2925407128, "lat": 40.426124, "lon": -121.335263}, {"type": "node", "id": 2925407129, "lat": 40.4262075, "lon": -121.335337}, {"type": "node", "id": 2925407130, "lat": 40.4263119, "lon": -121.3353809}, {"type": "node", "id": 2925407131, "lat": 40.4264163, "lon": -121.3353918}, {"type": "node", "id": 2925407132, "lat": 40.4265373, "lon": -121.3353918}, {"type": "node", "id": 2925407133, "lat": 40.4267482, "lon": -121.3354165}, {"type": "node", "id": 2925407134, "lat": 40.4268797, "lon": -121.3354494}, {"type": "node", "id": 2925407135, "lat": 40.4269485, "lon": -121.3354851}, {"type": "node", "id": 2925407136, "lat": 40.4271427, "lon": -121.3356989}, {"type": "node", "id": 2925407137, "lat": 40.4274745, "lon": -121.3361102}, {"type": "node", "id": 2925407138, "lat": 40.4280152, "lon": -121.3366806}, {"type": "node", "id": 2925407139, "lat": 40.4282427, "lon": -121.3369137}, {"type": "node", "id": 2925407140, "lat": 40.4283157, "lon": -121.3370562}, {"type": "node", "id": 2925407141, "lat": 40.4284222, "lon": -121.3372509}, {"type": "node", "id": 2925407142, "lat": 40.4286518, "lon": -121.3377801}, {"type": "node", "id": 2925407143, "lat": 40.428873, "lon": -121.3383094}, {"type": "node", "id": 2925407144, "lat": 40.4291652, "lon": -121.3389099}, {"type": "node", "id": 2925407145, "lat": 40.4294971, "lon": -121.3395872}, {"type": "node", "id": 2925407146, "lat": 40.4296015, "lon": -121.339812}, {"type": "node", "id": 2925407147, "lat": 40.4296578, "lon": -121.3399573}, {"type": "node", "id": 2925407148, "lat": 40.4297747, "lon": -121.3403961}, {"type": "node", "id": 2925407149, "lat": 40.4299501, "lon": -121.3409417}, {"type": "node", "id": 2925407150, "lat": 40.4300335, "lon": -121.3412214}, {"type": "node", "id": 2925407151, "lat": 40.4301149, "lon": -121.3414874}, {"type": "node", "id": 2925407152, "lat": 40.4301963, "lon": -121.3417534}, {"type": "node", "id": 2925407153, "lat": 40.4302861, "lon": -121.3420824}, {"type": "node", "id": 2925407154, "lat": 40.4303529, "lon": -121.3423566}, {"type": "node", "id": 2925407155, "lat": 40.4304489, "lon": -121.3428063}, {"type": "node", "id": 2925407156, "lat": 40.4305345, "lon": -121.3431573}, {"type": "node", "id": 2925407157, "lat": 40.4305825, "lon": -121.3434123}, {"type": "node", "id": 2925407158, "lat": 40.4306305, "lon": -121.3437633}, {"type": "node", "id": 2925407159, "lat": 40.4307098, "lon": -121.344361}, {"type": "node", "id": 2925407160, "lat": 40.4307432, "lon": -121.3447038}, {"type": "node", "id": 2925407161, "lat": 40.4307453, "lon": -121.344893}, {"type": "node", "id": 2925407162, "lat": 40.4307578, "lon": -121.3450575}, {"type": "node", "id": 2925407163, "lat": 40.4307724, "lon": -121.3451974}, {"type": "node", "id": 2925407164, "lat": 40.4308058, "lon": -121.3453208}, {"type": "node", "id": 2925407165, "lat": 40.4309561, "lon": -121.3457183}, {"type": "node", "id": 2925407167, "lat": 40.4310938, "lon": -121.346009}, {"type": "node", "id": 2925407168, "lat": 40.4313193, "lon": -121.3464285}, {"type": "node", "id": 2925407169, "lat": 40.4316407, "lon": -121.3469934}, {"type": "node", "id": 2925407170, "lat": 40.4317784, "lon": -121.3472237}, {"type": "node", "id": 2925407173, "lat": 40.4318745, "lon": -121.347391}, {"type": "node", "id": 2925407176, "lat": 40.4319454, "lon": -121.3474897}, {"type": "node", "id": 2925407178, "lat": 40.4320519, "lon": -121.3476213}, {"type": "node", "id": 2925407183, "lat": 40.4323057, "lon": -121.3478848}, {"type": "node", "id": 2925407186, "lat": 40.4325361, "lon": -121.3481067}, {"type": "node", "id": 2925407191, "lat": 40.4329076, "lon": -121.348411}, {"type": "node", "id": 2925407307, "lat": 40.4333522, "lon": -121.348773}, {"type": "node", "id": 2925407311, "lat": 40.433467, "lon": -121.3488525}, {"type": "node", "id": 2925407315, "lat": 40.4335525, "lon": -121.3489567}, {"type": "node", "id": 2977225387, "lat": 40.6435423, "lon": -121.248278}, {"type": "node", "id": 7196637808, "lat": 40.6463358, "lon": -121.2841925}, {"type": "node", "id": 7196637809, "lat": 40.6463453, "lon": -121.2842961}, {"type": "node", "id": 8836689092, "lat": 40.4277161, "lon": -121.3363647, "tags": {"highway": "trailhead", "name": "Mount Harkness-Warner Valley Trailhead"}}, {"type": "node", "id": 8837521443, "lat": 40.5872857, "lon": -121.2944314}, {"type": "node", "id": 8837521444, "lat": 40.5871523, "lon": -121.2938839}, {"type": "node", "id": 8837521445, "lat": 40.5870086, "lon": -121.2933973}, {"type": "node", "id": 8837521446, "lat": 40.5868392, "lon": -121.2930999}, {"type": "node", "id": 8837521447, "lat": 40.5866647, "lon": -121.2927417}, {"type": "node", "id": 8837521448, "lat": 40.5866031, "lon": -121.2924578}, {"type": "node", "id": 8837521449, "lat": 40.5865928, "lon": -121.2921537}, {"type": "node", "id": 8837521450, "lat": 40.5866032, "lon": -121.2916}, {"type": "node", "id": 8837521451, "lat": 40.5866056, "lon": -121.2913083}, {"type": "node", "id": 8837521452, "lat": 40.5865951, "lon": -121.2908911}, {"type": "node", "id": 8837521453, "lat": 40.5865596, "lon": -121.2902442}, {"type": "node", "id": 8837521454, "lat": 40.5865519, "lon": -121.2899874}, {"type": "node", "id": 8837521455, "lat": 40.5865455, "lon": -121.2897356}, {"type": "node", "id": 8837521456, "lat": 40.5865301, "lon": -121.2894281}, {"type": "node", "id": 8837521457, "lat": 40.5865057, "lon": -121.2891865}, {"type": "node", "id": 8837521458, "lat": 40.5864787, "lon": -121.2888502}, {"type": "node", "id": 8837521459, "lat": 40.5864467, "lon": -121.2886441}, {"type": "node", "id": 8837521460, "lat": 40.5864107, "lon": -121.2885123}, {"type": "node", "id": 8837521461, "lat": 40.586371, "lon": -121.2882588}, {"type": "node", "id": 8837521462, "lat": 40.5862747, "lon": -121.2877925}, {"type": "node", "id": 8837521463, "lat": 40.5860925, "lon": -121.286973}, {"type": "node", "id": 8837521464, "lat": 40.5859796, "lon": -121.2865269}, {"type": "node", "id": 8837521465, "lat": 40.5859231, "lon": -121.2862262}, {"type": "node", "id": 8837521466, "lat": 40.5858705, "lon": -121.2859643}, {"type": "node", "id": 8837521467, "lat": 40.5857871, "lon": -121.2855216}, {"type": "node", "id": 8837521468, "lat": 40.5856973, "lon": -121.2851346}, {"type": "node", "id": 8837521469, "lat": 40.585678, "lon": -121.2848812}, {"type": "node", "id": 8837521470, "lat": 40.5857037, "lon": -121.2845027}, {"type": "node", "id": 8837521471, "lat": 40.5857999, "lon": -121.284234}, {"type": "node", "id": 8837521472, "lat": 40.5859436, "lon": -121.2839975}, {"type": "node", "id": 8837521473, "lat": 40.5862218, "lon": -121.2835345}, {"type": "node", "id": 8837521474, "lat": 40.5862832, "lon": -121.2833003}, {"type": "node", "id": 8837521475, "lat": 40.5863123, "lon": -121.282947}, {"type": "node", "id": 8837521476, "lat": 40.5862929, "lon": -121.2825978}, {"type": "node", "id": 8837521477, "lat": 40.5862056, "lon": -121.2822359}, {"type": "node", "id": 8837521478, "lat": 40.5860245, "lon": -121.2816739}, {"type": "node", "id": 8837521479, "lat": 40.5858402, "lon": -121.2809671}, {"type": "node", "id": 8837521480, "lat": 40.5857271, "lon": -121.2804519}, {"type": "node", "id": 8837521481, "lat": 40.5855492, "lon": -121.279826}, {"type": "node", "id": 8837521482, "lat": 40.5854587, "lon": -121.2793194}, {"type": "node", "id": 8837521483, "lat": 40.5853746, "lon": -121.2787062}, {"type": "node", "id": 8837521484, "lat": 40.5853229, "lon": -121.2781996}, {"type": "node", "id": 8837521485, "lat": 40.5851968, "lon": -121.2777057}, {"type": "node", "id": 8837521486, "lat": 40.5851127, "lon": -121.2774758}, {"type": "node", "id": 8837521487, "lat": 40.5849607, "lon": -121.2773097}, {"type": "node", "id": 8837521488, "lat": 40.5847538, "lon": -121.2772586}, {"type": "node", "id": 8837521489, "lat": 40.5843981, "lon": -121.2772288}, {"type": "node", "id": 8837521490, "lat": 40.5840521, "lon": -121.2772501}, {"type": "node", "id": 8837521491, "lat": 40.5837772, "lon": -121.2772458}, {"type": "node", "id": 8837521492, "lat": 40.5835638, "lon": -121.2773097}, {"type": "node", "id": 8837521493, "lat": 40.5831952, "lon": -121.2774161}, {"type": "node", "id": 8837521494, "lat": 40.5828524, "lon": -121.2775524}, {"type": "node", "id": 8837521495, "lat": 40.5823124, "lon": -121.2776759}, {"type": "node", "id": 8837521496, "lat": 40.5820731, "lon": -121.277727}, {"type": "node", "id": 8837521497, "lat": 40.5816043, "lon": -121.2776972}, {"type": "node", "id": 8837521498, "lat": 40.5813585, "lon": -121.2776844}, {"type": "node", "id": 8837521499, "lat": 40.5809996, "lon": -121.2777142}, {"type": "node", "id": 8837521500, "lat": 40.5807441, "lon": -121.2777014}, {"type": "node", "id": 8837521501, "lat": 40.5805986, "lon": -121.2776588}, {"type": "node", "id": 8837521502, "lat": 40.5803011, "lon": -121.2775269}, {"type": "node", "id": 8837521503, "lat": 40.580023, "lon": -121.2773395}, {"type": "node", "id": 8837521504, "lat": 40.5798936, "lon": -121.2771735}, {"type": "node", "id": 8837521505, "lat": 40.5797804, "lon": -121.2769052}, {"type": "node", "id": 8837521506, "lat": 40.5796673, "lon": -121.2767605}, {"type": "node", "id": 8837521507, "lat": 40.5795185, "lon": -121.276654}, {"type": "node", "id": 8837521508, "lat": 40.5793536, "lon": -121.2766668}, {"type": "node", "id": 8837521509, "lat": 40.579179, "lon": -121.2767307}, {"type": "node", "id": 8837521510, "lat": 40.5790108, "lon": -121.276803}, {"type": "node", "id": 8837521511, "lat": 40.5788815, "lon": -121.2768073}, {"type": "node", "id": 8837521512, "lat": 40.578765, "lon": -121.2767477}, {"type": "node", "id": 8837521513, "lat": 40.5786292, "lon": -121.2766114}, {"type": "node", "id": 8837521514, "lat": 40.5785031, "lon": -121.2763773}, {"type": "node", "id": 8837521515, "lat": 40.578474, "lon": -121.2760962}, {"type": "node", "id": 8837521516, "lat": 40.5784384, "lon": -121.2757556}, {"type": "node", "id": 8837524417, "lat": 40.5785031, "lon": -121.2752319}, {"type": "node", "id": 8837524418, "lat": 40.5786519, "lon": -121.2748232}, {"type": "node", "id": 8837524419, "lat": 40.5789429, "lon": -121.2742484}, {"type": "node", "id": 8837524420, "lat": 40.5795153, "lon": -121.2733713}, {"type": "node", "id": 8837524421, "lat": 40.5797901, "lon": -121.272937}, {"type": "node", "id": 8837524422, "lat": 40.5799421, "lon": -121.2728433}, {"type": "node", "id": 8837524423, "lat": 40.5806536, "lon": -121.2726432}, {"type": "node", "id": 8837524424, "lat": 40.5809252, "lon": -121.272524}, {"type": "node", "id": 8837524425, "lat": 40.5814102, "lon": -121.2722047}, {"type": "node", "id": 8837524426, "lat": 40.5818468, "lon": -121.2718342}, {"type": "node", "id": 8837524427, "lat": 40.5822445, "lon": -121.2716469}, {"type": "node", "id": 8837524428, "lat": 40.5823674, "lon": -121.2714638}, {"type": "node", "id": 8837524429, "lat": 40.5824288, "lon": -121.2711871}, {"type": "node", "id": 8837524430, "lat": 40.582555, "lon": -121.2697309}, {"type": "node", "id": 8837524431, "lat": 40.5826261, "lon": -121.2690923}, {"type": "node", "id": 8837524432, "lat": 40.582749, "lon": -121.2685771}, {"type": "node", "id": 8837524433, "lat": 40.5832316, "lon": -121.2672134}, {"type": "node", "id": 8837524434, "lat": 40.5831667, "lon": -121.2671292}, {"type": "node", "id": 8837524435, "lat": 40.5831973, "lon": -121.2673529}, {"type": "way", "id": 7916583, "nodes": [58535852, 58535853, 58535855, 58535861, 58535862, 58207573, 58535867, 58535869, 58535872, 58535874, 58535875, 58535879, 58535880, 58535883, 58535884, 58535890, 58535892, 58535895, 58535897, 58535901, 58535903, 58535905, 58535906, 58535910, 58535911, 58535914, 58535917, 58535918, 58535920, 58535922, 58535924, 58535927, 58535929, 58535931, 58535933, 58535934, 58535935, 58535937, 58535939, 58535941, 58535943, 58535945, 58535947, 58535950, 58535953, 58535955, 58535957, 58535958, 58535962, 58535964, 58535966, 58535968, 58535970, 58535972, 58535973, 58535977, 58535978, 58535980, 58535981, 58261706, 58535984, 58535986, 58535988, 58535990, 58535992, 58535994, 58535996, 58535998, 58536000, 58536002, 58536005, 58536007, 58536009, 58536011, 58536012, 58536014, 58536015, 58536016, 58536017, 58536019, 58536021, 58536023, 58536025, 58536027, 58536029, 58536031, 58536033, 58536035, 58536037, 58536039, 58536041, 58536043, 58536046, 58536050, 58536052, 58473443, 58536053, 58536054, 58536056, 58536059, 58536061, 58536063, 58536065, 58536067, 58536068, 58536071, 58536073, 58536074, 58536076, 58536079, 58536080, 58536082, 58536085, 58536088, 58536089, 58536091, 58536093, 58536095, 58536097, 58536099, 58536101, 58536103, 58536105, 58536107, 58536109, 58536111, 58536113, 58536115, 58536117, 58536119, 58536121, 58536123, 58536124, 58536127, 58536129, 58536131, 58536133, 58536135, 58536137, 58536139, 58536141, 58536143, 58536145, 58536147, 58536149, 58536151, 58536153, 58536155, 58536157, 58536159, 58536161, 58536163, 58536165, 58536166, 58536168, 58414597, 58536171, 58536173, 58536175, 58536177, 58536179, 58536181, 58536183, 58536185, 58536187, 58536189, 58536191, 58536193, 58536195, 58536197, 58536199, 58536201, 58536203, 58536205, 58536207, 58536209, 58536211, 58536213, 58536215, 58536217, 58536219, 58536221, 58536223, 58536225, 58536227, 58536229, 58536231, 58536233, 58536235, 58536237, 58536239, 58536241, 58536243, 58536245, 58536247, 58536249, 58536251, 58536253, 58536255, 58536257, 58536259, 58536261, 58536263, 58536265, 58536267, 58536269, 58536271, 58536273, 58536275, 58536277, 58536279, 58536281, 58536283, 58536285, 58536287, 58536289, 58536291, 58536293, 58536295, 58536296, 58536298, 58536301, 58536303, 58536305, 58536306, 58536308, 58536311, 58536313, 58536315, 58536316, 58536318, 58536321, 58536322, 58536325, 58536326, 58536328, 58536331, 58536332, 58536335, 58536337, 58536339, 58536341, 58536343, 58536345, 58536347, 58536348, 58536350, 58536352, 58536354, 58536357, 58536358, 58536361, 58536362, 58536364, 58536367, 58536368, 58536371, 58536373, 58536375, 58536377, 58536379, 58536381, 58536384, 58536385, 58536387, 58536389, 58536391, 58536393, 58536395, 58536397, 58536399, 58536401, 58536403, 58536405, 58536407, 58536409, 58536410, 58536411, 58536412, 58536413, 58536414, 58536415, 58536416, 58536417, 58536418, 58536419, 58536420, 58536421, 58536422, 58536423, 58536424, 58536425, 58536426, 58536427, 58536428, 58536429, 58536430, 58536431, 58536432, 58536433, 58536434, 58536435, 58536436, 58536437, 58536438, 58536439, 58536440, 58536441, 58536442, 58536445], "tags": {"highway": "unclassified", "name": "Halls Flat Road", "name_1": "Forest Route 33N18", "surface": "unpaved", "tiger:cfcc": "A41", "tiger:county": "Lassen, CA", "tiger:name_base": "Halls Flat", "tiger:name_base_1": "Forest Route 33N18", "tiger:name_type": "Rd", "tiger:reviewed": "no"}}, {"type": "way", "id": 288994605, "nodes": [2925406575, 2925406571, 2925406570, 2925406572, 2925406573, 2925406576, 2925406578, 2925406584, 2925406585, 2925406586, 2925406587, 2925406588, 2925406589, 2925406590, 90097154, 2925406592, 2925406593, 2925406594, 2925406595, 2925406596, 2925406597, 2925406598, 2925406599, 2925406600, 2925407001, 2925407002, 2925407003, 2925407004, 2925407005, 2925407006, 2925407007, 2925407008, 2925407009, 2925407010, 2925407011, 2925407012, 2925407013, 2925407014, 2925407015, 2925407016, 2925407017, 2925407018, 2925407019, 2925407020, 2925407021, 2925407022, 2925407023, 2925407024, 2925407025, 2925407026, 2925407027, 2925407028, 2925407029, 2925407030, 2925407031, 2925407032, 2925407033, 90219602, 2925407034, 2925407035, 2925407036, 2925407037, 2925407038, 2925407039, 2925407040, 2925407041, 2925407042, 2925407043, 2925407044, 2925407045, 2925407046, 2925407047, 2925407048, 2925407049, 2925407050, 2925407051, 2925407052, 2925407053, 2925407054, 2925407055, 2925407056, 2925407057, 2925407059, 2925407060, 2925407061, 2925407062, 2925407063, 2925407064, 2925407065, 2925407066, 2925407067, 2925407068, 2925407069, 2925407070, 2925407071, 2925407072, 2925407073, 2925407074, 2925407075, 2925407076, 2925407077, 2925407078, 2925407079, 2925407080, 2925407081, 2925407082, 2925407083, 2925407084, 2925407085, 2925407086, 2925407087, 2925407088, 2925407089, 2925407090, 2925407091, 2925407092, 2925407093, 2925407094, 2925407095, 2925407096, 2925407097, 2925407098, 2925407099, 2925407100, 2925407101, 2925407102, 2925407103, 2925407104, 2925407105, 2925407106, 2925407107, 2925407108, 2925407109, 2925407110, 2925407111, 2925407112, 2925407113, 2925407114, 2925407115, 2925407116, 2925407117, 2925407118, 2925407119, 2925407120, 2925407121, 2925407122, 2925407123, 2925407124, 2925407125, 2925407126, 2925407127, 2925407128, 2925407129, 2925407130, 2925407131, 2925407132, 2925407133, 2925407134, 2925407135, 2925407136, 2925407137, 8836689092, 2925407138, 2925407139, 2925407140, 2925407141, 2925407142, 2925407143, 2925407144, 2925407145, 2925407146, 2925407147, 2925407148, 2925407149, 2925407150, 2925407151, 2925407152, 2925407153, 2925407154, 2925407155, 2925407156, 2925407157, 2925407158, 2925407159, 2925407160, 2925407161, 2925407162, 2925407163, 2925407164, 2925407165, 2925407167, 2925407168, 2925407169, 2925407170, 2925407173, 2925407176, 2925407178, 2925407183, 2925407186, 2925407191, 2925407307, 2925407311, 2925407315, 90106407], "tags": {"highway": "unclassified", "name": "Chester-Warner Valley Road", "ref": "CR 312", "surface": "paved"}}, {"type": "way", "id": 441561706, "nodes": [57971429, 58719132, 58719133, 58719135, 58719137, 58719139, 58719140, 58719142, 58719144, 58719146, 58719147, 58504312, 58719150, 58719152, 58719154, 58719157, 58719158, 58719161, 58719162, 58719164, 58719169, 58719171, 58616827, 58719173, 58719175, 58719177, 58719179, 58719181, 58719183, 58207653, 58719188, 58719190, 58719193, 58719194, 58719196, 58719199, 58719202, 58719203, 58719205, 58719207, 58719209, 58719210, 58719212, 58719214, 58719216, 58719218, 58719220, 58719222, 58719224, 58719226, 58719228, 58319084, 58265404, 58719237, 58719239, 58719241, 58719243, 58719244, 58719247, 58719249, 58280692, 58719252, 58719254, 58719256, 58719258, 58566701, 58207641, 58719264, 58719266, 58280630, 58719269, 58719270, 58719275, 58719278, 58719279, 58719281, 58719284, 58548869, 58207634, 58719288, 58719290, 58719292, 58719294, 58209731, 58719297, 58719299, 58719301, 58719304, 58719305, 58719308, 58719311, 58719313, 58719315, 58719317, 58719319, 58719320, 58719322, 58719323, 58719324, 58719325, 58719326, 58719327, 58719328, 58719329, 58719330, 58719331, 58719332, 58719333, 58719334, 58719335, 58719336, 58719337, 58719338, 58719339, 58719340, 58719341, 58719342, 58719343, 58719344, 58719345, 58719348, 58719349, 58719350, 58719352, 58719354, 58052716, 58719355, 58719357, 58719359, 58719361, 58719363, 58719365, 58719368, 58719369, 58719371, 58719373, 58719376, 58719378, 58656774, 58719380, 58719382, 58719383, 58300812, 58719384, 58719387, 58719388, 58719390, 58719392, 58719393, 58719394, 58719395, 58719396, 58719397, 58719398, 58719400, 58719402, 58719404, 58719406, 58060654, 58719410, 58719412, 58719414, 58719416, 58719417, 58719419, 58719422, 58719424, 58719426, 58719428, 58719430, 58719432, 58719434, 58719436, 58719438, 58719440, 58719442, 58719444, 58719446, 58719448, 58348320, 58087226, 58719452, 58719454, 58719455, 58719458, 58087390, 2977225387, 58719463, 58511994, 58536445, 58141568, 58719469, 58719472, 58719474, 58719475, 58719477, 58719480, 58719483, 58719487, 58719493, 58719495, 58574564, 58719502, 58719504, 58719506, 58141307, 7196637808, 7196637809, 58719513, 58719521, 58719523, 58719525, 58719527, 58719529, 58719530, 58719533, 58719536, 58719537, 58719538, 58719539, 58719540, 58646014, 58719541, 58719542, 58305195, 58719543, 58719545, 58719547, 58719549, 58719551, 58719553], "tags": {"NHS": "yes", "hgv": "designated", "hgv:national_network": "terminal_access", "highway": "trunk", "lanes": "2", "maxspeed": "65 mph", "name": "Feather Lake Highway", "ref": "CA 44", "source:hgv:national_network": "Caltrans http://www.dot.ca.gov/hq/traffops/trucks/truckmap/", "tiger:cfcc": "A31:A41", "tiger:county": "Lassen, CA", "tiger:name_base": "Feather Lake", "tiger:name_base_1": "State Route 44", "tiger:name_type": "Hwy", "tiger:reviewed": "no"}}, {"type": "way", "id": 591678211, "nodes": [57980364, 58548159, 58548162, 58548164, 58182124, 58548166, 58548168, 58548170, 58548171, 58548173, 58548175, 58548178, 58548180, 58548182, 58548184, 58548185, 58548186, 58548189, 58548191, 58548193, 58548195, 58548197, 58548199, 58548201, 58548203, 58548205, 58548207, 58548209, 58548211, 58548213, 58548215, 58548217, 58548219, 58548221, 58548222, 58548224, 58548226, 58548228, 58548230, 58548232, 58548234, 58548236, 58548238, 58548240, 58548242, 58548244, 58548246, 58548248, 58548250, 58548252, 58548254, 58548256, 58548258, 58548260, 58474081, 58558583, 58287084, 58548265, 58548267, 58548269, 58548271, 58548273, 58304776, 58548276, 58548278, 58548280, 58548282, 58548284, 58548286, 58548288, 58548290, 58548291, 58548293, 58548295, 58535852, 58548298, 58548300, 58548303, 58548304, 58548306, 58548308, 58548310, 58548312, 58548314, 58548316, 58548318, 58548320, 58548322, 58548323, 58548324, 58548325, 58548326, 58548327, 58548328, 58548329, 58548330, 58548331, 58548332, 58548333, 58548334, 58548335, 58548336, 58548337, 58548338, 58548339, 58548340, 58548341, 58548342, 58548343, 58548346, 58548348, 58548349, 58548350, 58548351, 58548353, 58548355, 58548357, 58548359, 58548362, 58548363, 58548364, 58548365, 58548367, 58548369, 58548371, 58548373, 58548375, 58548377, 58548379, 58548381, 58548383, 58548385, 58548387, 58548388, 58548389, 58548390, 58548392, 58548394, 58548396, 58548398, 58548402, 58548404, 58548406, 58548408, 58548411, 58548412, 58548415, 58548417, 58548418, 58548420, 58548423, 58548424, 58548425, 58548426, 58548428, 58548430, 58548431, 58548433, 58548434, 58558564, 58548441, 58247691, 58548446, 58548447, 58382852, 58548450, 58548452, 58548454, 58548456, 58548460, 58548463, 58548465, 58548467, 58548469, 58548471, 58548473, 58548475, 58548476, 58548477, 58548478, 58548480, 58548482, 58548484, 58548485, 58548487, 58548490, 58548492, 58548494, 58548495, 58207729, 58548496, 58548498, 58548500, 58548503, 58548504, 58548507, 58548508, 58548510, 58548513, 58548514, 58548515, 58548516, 58548518, 58548520, 58548522, 58548525, 58548526, 58548528, 58548530, 58548532, 58548533, 58548535, 58548537, 58548539, 58548541, 58548542, 58548544, 58060586, 58490682, 58548548, 58548550, 58548551, 58548552, 58548553, 58548556, 58548558, 58548559, 58548561, 58548564, 58548565, 58548566, 58548568, 58548569, 58548571, 58548573, 58548575, 58548577, 58548578, 58548580, 58548583, 58514128, 58548585, 58187068], "tags": {"highway": "unclassified", "name": "Pittville Road", "surface": "unpaved", "tiger:cfcc": "A41", "tiger:county": "Lassen, CA", "tiger:name_base": "Pittville", "tiger:name_type": "Rd", "tiger:reviewed": "no"}}, {"type": "way", "id": 954801969, "nodes": [58575015, 8837521443, 8837521444, 8837521445, 8837521446, 8837521447, 8837521448, 8837521449, 8837521450, 8837521451, 8837521452, 8837521453, 8837521454, 8837521455, 8837521456, 8837521457, 8837521458, 8837521459, 8837521460, 8837521461, 8837521462, 8837521463, 8837521464, 8837521465, 8837521466, 8837521467, 8837521468, 8837521469, 8837521470, 8837521471, 8837521472, 8837521473, 8837521474, 8837521475, 8837521476, 8837521477, 8837521478, 8837521479, 8837521480, 8837521481, 8837521482, 8837521483, 8837521484, 8837521485, 8837521486, 8837521487, 8837521488, 8837521489, 8837521490, 8837521491, 8837521492, 8837521493, 8837521494, 8837521495, 8837521496, 8837521497, 8837521498, 8837521499, 8837521500, 8837521501, 8837521502, 8837521503, 8837521504, 8837521505, 8837521506, 8837521507, 8837521508, 8837521509, 8837521510, 8837521511, 8837521512, 8837521513, 8837521514, 8837521515, 8837521516, 8837524417, 8837524418, 8837524419, 8837524420, 8837524421, 8837524422, 8837524423, 8837524424, 8837524425, 8837524426, 8837524427, 8837524428, 8837524429, 8837524430, 8837524431, 8837524432, 8837524435, 8837524433, 58144391, 8837524434, 58144392, 58144395, 58144397, 58144398, 58144400, 58144402, 58144404, 58144406, 58144408, 58144411], "tags": {"highway": "unclassified", "ref": "FS 32N09", "surface": "unpaved", "tiger:cfcc": "A51", "tiger:county": "Lassen, CA", "tiger:reviewed": "no"}}]}