{"version": 0.6, "generator": "Overpass API 0.7.62.7 375dc00a", "osm3s": {"timestamp_osm_base": "2025-08-09T13:05:08Z", "copyright": "The data included in this document is from www.openstreetmap.org. The data is made available under ODbL."}, "elements": [{"type": "node", "id": 81078355, "lat": 65.0648991, "lon": 20.0424287}, {"type": "node", "id": 81078360, "lat": 65.0642589, "lon": 20.0440371}, {"type": "node", "id": 81078365, "lat": 65.064005, "lon": 20.0446141}, {"type": "node", "id": 81078370, "lat": 65.0635405, "lon": 20.0455119, "tags": {"created_by": "JOSM"}}, {"type": "node", "id": 81078375, "lat": 65.0626448, "lon": 20.0470085}, {"type": "node", "id": 81078380, "lat": 65.0615876, "lon": 20.0483836}, {"type": "node", "id": 81078386, "lat": 65.0590399, "lon": 20.0510014}, {"type": "node", "id": 81078391, "lat": 65.0569821, "lon": 20.0531762}, {"type": "node", "id": 81078396, "lat": 65.055618, "lon": 20.0546393}, {"type": "node", "id": 81078400, "lat": 65.0539049, "lon": 20.0568777}, {"type": "node", "id": 81078405, "lat": 65.0523171, "lon": 20.05931, "tags": {"created_by": "JOSM"}}, {"type": "node", "id": 81078408, "lat": 65.0512589, "lon": 20.0613279, "tags": {"created_by": "JOSM"}}, {"type": "node", "id": 81078413, "lat": 65.0503387, "lon": 20.063673, "tags": {"created_by": "JOSM"}}, {"type": "node", "id": 81078418, "lat": 65.0494875, "lon": 20.0653637, "tags": {"created_by": "JOSM"}}, {"type": "node", "id": 81078422, "lat": 65.0442877, "lon": 20.0763259, "tags": {"created_by": "JOSM"}}, {"type": "node", "id": 81078427, "lat": 65.042953, "lon": 20.0789437, "tags": {"created_by": "JOSM"}}, {"type": "node", "id": 81078432, "lat": 65.0415493, "lon": 20.0813979, "tags": {"created_by": "JOSM"}}, {"type": "node", "id": 81078435, "lat": 65.0388566, "lon": 20.0866336, "tags": {"created_by": "JOSM"}}, {"type": "node", "id": 81078440, "lat": 65.0376828, "lon": 20.0895241, "tags": {"created_by": "JOSM"}}, {"type": "node", "id": 81078442, "lat": 65.0367852, "lon": 20.0921419, "tags": {"created_by": "JOSM"}}, {"type": "node", "id": 81078446, "lat": 65.0351478, "lon": 20.0974609, "tags": {"created_by": "JOSM"}}, {"type": "node", "id": 81078451, "lat": 65.0341602, "lon": 20.100683, "tags": {"created_by": "JOSM"}}, {"type": "node", "id": 81078456, "lat": 65.0334705, "lon": 20.1026677, "tags": {"created_by": "JOSM"}}, {"type": "node", "id": 81078458, "lat": 65.0328259, "lon": 20.1043039, "tags": {"created_by": "JOSM"}}, {"type": "node", "id": 81078464, "lat": 65.0319972, "lon": 20.1059946, "tags": {"created_by": "JOSM"}}, {"type": "node", "id": 81078469, "lat": 65.0303566, "lon": 20.1088207}, {"type": "node", "id": 81078474, "lat": 65.0267479, "lon": 20.1146116, "tags": {"created_by": "JOSM"}}, {"type": "node", "id": 81078480, "lat": 65.0258959, "lon": 20.1164113, "tags": {"created_by": "JOSM"}}, {"type": "node", "id": 81078483, "lat": 65.0248597, "lon": 20.1187019, "tags": {"created_by": "JOSM"}}, {"type": "node", "id": 81078488, "lat": 65.0230635, "lon": 20.1235558, "tags": {"created_by": "JOSM"}}, {"type": "node", "id": 81078493, "lat": 65.0221884, "lon": 20.1263918, "tags": {"created_by": "JOSM"}}, {"type": "node", "id": 81078498, "lat": 65.021152, "lon": 20.1307548, "tags": {"created_by": "JOSM"}}, {"type": "node", "id": 81078503, "lat": 65.0206684, "lon": 20.1338089, "tags": {"created_by": "JOSM"}}, {"type": "node", "id": 81078508, "lat": 65.0202308, "lon": 20.1363722, "tags": {"created_by": "JOSM"}}, {"type": "node", "id": 81078514, "lat": 65.0198393, "lon": 20.1384992, "tags": {"created_by": "JOSM"}}, {"type": "node", "id": 81078519, "lat": 65.0192635, "lon": 20.141008, "tags": {"created_by": "JOSM"}}, {"type": "node", "id": 81078524, "lat": 65.0186185, "lon": 20.1433531, "tags": {"created_by": "JOSM"}}, {"type": "node", "id": 81078528, "lat": 65.0176972, "lon": 20.1465163, "tags": {"created_by": "JOSM"}}, {"type": "node", "id": 81078531, "lat": 65.0157623, "lon": 20.1516974, "tags": {"created_by": "JOSM"}}, {"type": "node", "id": 81078535, "lat": 65.0132744, "lon": 20.1585147, "tags": {"created_by": "JOSM"}}, {"type": "node", "id": 81078540, "lat": 65.0103485, "lon": 20.1665318, "tags": {"created_by": "JOSM"}}, {"type": "node", "id": 81078547, "lat": 65.008367, "lon": 20.1725309, "tags": {"created_by": "JOSM"}}, {"type": "node", "id": 81078551, "lat": 65.0071919, "lon": 20.1764031, "tags": {"created_by": "JOSM"}}, {"type": "node", "id": 81078556, "lat": 65.0060185, "lon": 20.180329}, {"type": "node", "id": 81078560, "lat": 65.0046374, "lon": 20.1846351}, {"type": "node", "id": 81078565, "lat": 65.0039205, "lon": 20.1866853}, {"type": "node", "id": 81078570, "lat": 65.0021285, "lon": 20.1910551}, {"type": "node", "id": 81078575, "lat": 64.9991258, "lon": 20.1978911, "tags": {"created_by": "JOSM"}}, {"type": "node", "id": 81078579, "lat": 64.9964288, "lon": 20.2044902, "tags": {"created_by": "JOSM"}}, {"type": "node", "id": 81078584, "lat": 64.994308, "lon": 20.2102167, "tags": {"created_by": "JOSM"}}, {"type": "node", "id": 81078589, "lat": 64.991795, "lon": 20.2167613, "tags": {"created_by": "JOSM"}}, {"type": "node", "id": 81292279, "lat": 64.9910535, "lon": 20.2183993, "tags": {"created_by": "JOSM"}}, {"type": "node", "id": 81292280, "lat": 64.9898882, "lon": 20.2202368, "tags": {"created_by": "JOSM"}}, {"type": "node", "id": 81292281, "lat": 64.9886119, "lon": 20.2222056, "tags": {"created_by": "JOSM"}}, {"type": "node", "id": 81292282, "lat": 64.9867662, "lon": 20.2244348, "tags": {"created_by": "JOSM"}}, {"type": "node", "id": 81292283, "lat": 64.9851156, "lon": 20.2264713, "tags": {"created_by": "JOSM"}}, {"type": "node", "id": 81292285, "lat": 64.9825902, "lon": 20.2290307, "tags": {"created_by": "JOSM"}}, {"type": "node", "id": 81292286, "lat": 64.9813136, "lon": 20.2299495, "tags": {"created_by": "JOSM"}}, {"type": "node", "id": 81292287, "lat": 64.9804532, "lon": 20.2302776, "tags": {"created_by": "JOSM"}}, {"type": "node", "id": 81292288, "lat": 64.9792874, "lon": 20.2305401, "tags": {"created_by": "JOSM"}}, {"type": "node", "id": 81292289, "lat": 64.9757066, "lon": 20.2308683, "tags": {"created_by": "JOSM"}}, {"type": "node", "id": 81292290, "lat": 64.974846, "lon": 20.2309995, "tags": {"created_by": "JOSM"}}, {"type": "node", "id": 81292291, "lat": 64.9738466, "lon": 20.2315245, "tags": {"created_by": "JOSM"}}, {"type": "node", "id": 81292292, "lat": 64.9729027, "lon": 20.2322464, "tags": {"created_by": "JOSM"}}, {"type": "node", "id": 81292293, "lat": 64.9714868, "lon": 20.2337558, "tags": {"created_by": "JOSM"}}, {"type": "node", "id": 81292294, "lat": 64.9702373, "lon": 20.2353965, "tags": {"created_by": "JOSM"}}, {"type": "node", "id": 81292295, "lat": 64.9694599, "lon": 20.2370371, "tags": {"created_by": "JOSM"}}, {"type": "node", "id": 81292296, "lat": 64.966211, "lon": 20.2449779, "tags": {"created_by": "JOSM"}}, {"type": "node", "id": 81292297, "lat": 64.9652946, "lon": 20.2472092, "tags": {"created_by": "JOSM"}}, {"type": "node", "id": 81292298, "lat": 64.9644614, "lon": 20.2490467, "tags": {"created_by": "JOSM"}}, {"type": "node", "id": 81292300, "lat": 64.9632395, "lon": 20.2511467, "tags": {"created_by": "JOSM"}}, {"type": "node", "id": 81292301, "lat": 64.9606565, "lon": 20.2550187, "tags": {"created_by": "JOSM"}}, {"type": "node", "id": 81292302, "lat": 64.9582954, "lon": 20.2585625, "tags": {"created_by": "JOSM"}}, {"type": "node", "id": 81292303, "lat": 64.9559, "lon": 20.2620817}, {"type": "node", "id": 81292304, "lat": 64.9545491, "lon": 20.2637403}, {"type": "node", "id": 81292305, "lat": 64.9531004, "lon": 20.2651251, "tags": {"created_by": "JOSM"}}, {"type": "node", "id": 81292306, "lat": 64.9463204, "lon": 20.2713596, "tags": {"created_by": "JOSM"}}, {"type": "node", "id": 81292307, "lat": 64.9455422, "lon": 20.2722127, "tags": {"created_by": "JOSM"}}, {"type": "node", "id": 81292308, "lat": 64.9442916, "lon": 20.2739846, "tags": {"created_by": "JOSM"}}, {"type": "node", "id": 81292309, "lat": 64.9429019, "lon": 20.2763472, "tags": {"created_by": "JOSM"}}, {"type": "node", "id": 81292310, "lat": 64.9412342, "lon": 20.2796941, "tags": {"created_by": "JOSM"}}, {"type": "node", "id": 81292311, "lat": 64.9395942, "lon": 20.2839598, "tags": {"created_by": "JOSM"}}, {"type": "node", "id": 81292312, "lat": 64.9358413, "lon": 20.29341, "tags": {"created_by": "JOSM"}}, {"type": "node", "id": 81292313, "lat": 64.9343122, "lon": 20.2977413, "tags": {"created_by": "JOSM"}}, {"type": "node", "id": 81292314, "lat": 64.9322592, "lon": 20.3048182, "tags": {"created_by": "JOSM"}}, {"type": "node", "id": 81292315, "lat": 64.930559, "lon": 20.310485}, {"type": "node", "id": 81292316, "lat": 64.9299746, "lon": 20.312376, "tags": {"created_by": "JOSM"}}, {"type": "node", "id": 81292317, "lat": 64.9291125, "lon": 20.3145416, "tags": {"created_by": "JOSM"}}, {"type": "node", "id": 81292318, "lat": 64.9282226, "lon": 20.3166417, "tags": {"created_by": "JOSM"}}, {"type": "node", "id": 81292319, "lat": 64.9272215, "lon": 20.3186104, "tags": {"created_by": "JOSM"}}, {"type": "node", "id": 81292320, "lat": 64.9258882, "lon": 20.3205986}, {"type": "node", "id": 81292321, "lat": 64.9236615, "lon": 20.324123, "tags": {"created_by": "JOSM"}}, {"type": "node", "id": 81292322, "lat": 64.9217701, "lon": 20.3270762, "tags": {"created_by": "JOSM"}}, {"type": "node", "id": 81292323, "lat": 64.920268, "lon": 20.3298981, "tags": {"created_by": "JOSM"}}, {"type": "node", "id": 81292324, "lat": 64.9189049, "lon": 20.3324576, "tags": {"created_by": "JOSM"}}, {"type": "node", "id": 81292325, "lat": 64.9172582, "lon": 20.3354963}, {"type": "node", "id": 81292326, "lat": 64.9164692, "lon": 20.3368781}, {"type": "node", "id": 81292327, "lat": 64.9160455, "lon": 20.3375068}, {"type": "node", "id": 81292328, "lat": 64.9150407, "lon": 20.3384859}, {"type": "node", "id": 81292329, "lat": 64.9129044, "lon": 20.34105, "tags": {"created_by": "JOSM"}}, {"type": "node", "id": 81292330, "lat": 64.9086099, "lon": 20.3455828, "tags": {"created_by": "JOSM"}}, {"type": "node", "id": 81292331, "lat": 64.907441, "lon": 20.346961, "tags": {"created_by": "JOSM"}}, {"type": "node", "id": 81292332, "lat": 64.9064391, "lon": 20.3489297, "tags": {"created_by": "JOSM"}}, {"type": "node", "id": 81292333, "lat": 64.9051588, "lon": 20.3516204, "tags": {"created_by": "JOSM"}}, {"type": "node", "id": 81292334, "lat": 64.9039717, "lon": 20.3548482, "tags": {"created_by": "JOSM"}}, {"type": "node", "id": 81292335, "lat": 64.903101, "lon": 20.3578335, "tags": {"created_by": "JOSM"}}, {"type": "node", "id": 81292336, "lat": 64.902262, "lon": 20.3611943, "tags": {"created_by": "JOSM"}}, {"type": "node", "id": 81292337, "lat": 64.9013583, "lon": 20.3647899, "tags": {"created_by": "JOSM"}}, {"type": "node", "id": 81292338, "lat": 64.9006494, "lon": 20.3673051, "tags": {"created_by": "JOSM"}}, {"type": "node", "id": 81292339, "lat": 64.900004, "lon": 20.3690845, "tags": {"created_by": "JOSM"}}, {"type": "node", "id": 81292340, "lat": 64.8991242, "lon": 20.3707649, "tags": {"created_by": "JOSM"}}, {"type": "node", "id": 81292341, "lat": 64.8979302, "lon": 20.3722927, "tags": {"created_by": "JOSM"}}, {"type": "node", "id": 361488883, "lat": 65.0401547, "lon": 20.0838836}, {"type": "node", "id": 361489243, "lat": 64.9106292, "lon": 20.3432896}, {"type": "node", "id": 1418820326, "lat": 65.0538274, "lon": 20.0554555}, {"type": "node", "id": 1418820328, "lat": 65.0534927, "lon": 20.0574933}, {"type": "node", "id": 1418820333, "lat": 65.0569537, "lon": 20.0475938}, {"type": "node", "id": 1418820337, "lat": 65.0578556, "lon": 20.0452617, "tags": {"crossing": "zebra", "highway": "crossing"}}, {"type": "node", "id": 1418820338, "lat": 65.0584597, "lon": 20.0433957}, {"type": "node", "id": 1418820339, "lat": 65.059361, "lon": 20.0390209}, {"type": "node", "id": 1418820340, "lat": 65.0598598, "lon": 20.0366861}, {"type": "node", "id": 1418823971, "lat": 65.0199496, "lon": 20.1380128}, {"type": "node", "id": 1728700220, "lat": 65.0051298, "lon": 20.0906896}, {"type": "node", "id": 1729490949, "lat": 65.0038373, "lon": 20.1677291}, {"type": "node", "id": 1729490954, "lat": 65.0040783, "lon": 20.1179945}, {"type": "node", "id": 1729490975, "lat": 65.0037607, "lon": 20.1685381}, {"type": "node", "id": 1729491036, "lat": 65.0039468, "lon": 20.0961721}, {"type": "node", "id": 1729491078, "lat": 65.0040103, "lon": 20.112909}, {"type": "node", "id": 1729491109, "lat": 65.0068616, "lon": 20.1775982}, {"type": "node", "id": 1729491111, "lat": 65.0043095, "lon": 20.1022982}, {"type": "node", "id": 1729491122, "lat": 65.0031709, "lon": 20.1252536}, {"type": "node", "id": 1729491127, "lat": 65.0038924, "lon": 20.0976312}, {"type": "node", "id": 1729491131, "lat": 65.0031625, "lon": 20.126878}, {"type": "node", "id": 1729491135, "lat": 65.0042408, "lon": 20.1074652}, {"type": "node", "id": 1729491142, "lat": 65.0043949, "lon": 20.103281}, {"type": "node", "id": 1729491169, "lat": 65.0071969, "lon": 20.1410508}, {"type": "node", "id": 1729491182, "lat": 65.0075595, "lon": 20.1434755}, {"type": "node", "id": 1729491188, "lat": 65.0042317, "lon": 20.0946604}, {"type": "node", "id": 1729491227, "lat": 65.0049056, "lon": 20.0919234}, {"type": "node", "id": 1729491244, "lat": 65.0041281, "lon": 20.1175439}, {"type": "node", "id": 1729491253, "lat": 65.0038242, "lon": 20.1300215}, {"type": "node", "id": 1729491289, "lat": 65.0058098, "lon": 20.1751041}, {"type": "node", "id": 1729491291, "lat": 64.9977187, "lon": 20.2012875}, {"type": "node", "id": 1729491294, "lat": 65.0032078, "lon": 20.123434}, {"type": "node", "id": 1729491307, "lat": 65.003906, "lon": 20.0968855}, {"type": "node", "id": 1729491345, "lat": 65.0048215, "lon": 20.1331544}, {"type": "node", "id": 1729491357, "lat": 65.0041778, "lon": 20.170598}, {"type": "node", "id": 1729491403, "lat": 65.0075002, "lon": 20.1423661}, {"type": "node", "id": 1729491418, "lat": 65.0033982, "lon": 20.1284873}, {"type": "node", "id": 1729491465, "lat": 65.0039824, "lon": 20.1121966}, {"type": "node", "id": 1729491479, "lat": 65.0041825, "lon": 20.1163101}, {"type": "node", "id": 1729491486, "lat": 65.0040277, "lon": 20.0956045}, {"type": "node", "id": 1729491534, "lat": 65.0062359, "lon": 20.1561784}, {"type": "node", "id": 1729491580, "lat": 65.0039241, "lon": 20.0984627}, {"type": "node", "id": 1729491651, "lat": 65.0041773, "lon": 20.1168851}, {"type": "node", "id": 1729491691, "lat": 65.0032842, "lon": 20.1228397}, {"type": "node", "id": 1729491694, "lat": 65.0031754, "lon": 20.12417}, {"type": "node", "id": 1729491709, "lat": 65.005021, "lon": 20.1615429}, {"type": "node", "id": 1729491721, "lat": 65.0038332, "lon": 20.1695466}, {"type": "node", "id": 1729491739, "lat": 65.0058188, "lon": 20.1583886}, {"type": "node", "id": 1729491751, "lat": 65.0047288, "lon": 20.0925511}, {"type": "node", "id": 1729491755, "lat": 65.0051484, "lon": 20.0910549}, {"type": "node", "id": 1729491781, "lat": 65.0043956, "lon": 20.1039612}, {"type": "node", "id": 1729491788, "lat": 65.0074598, "lon": 20.1445269}, {"type": "node", "id": 1729491837, "lat": 65.003235, "lon": 20.1277685}, {"type": "node", "id": 1729491849, "lat": 65.0060314, "lon": 20.1574938}, {"type": "node", "id": 1762201807, "lat": 64.9333226, "lon": 20.3013065}, {"type": "node", "id": 1762201811, "lat": 64.9384833, "lon": 20.2868972}, {"type": "node", "id": 1762303460, "lat": 65.0044665, "lon": 20.1644409}, {"type": "node", "id": 1762303549, "lat": 64.9477832, "lon": 20.2700247}, {"type": "node", "id": 1762306953, "lat": 64.9614569, "lon": 20.2538189}, {"type": "node", "id": 1769020374, "lat": 64.8997628, "lon": 20.36963}, {"type": "node", "id": 1772029064, "lat": 64.9710829, "lon": 20.2342862}, {"type": "node", "id": 1834192607, "lat": 65.063286, "lon": 20.0459636}, {"type": "node", "id": 1852714499, "lat": 65.0348409, "lon": 20.0984782}, {"type": "node", "id": 1868866249, "lat": 65.0243866, "lon": 20.1199804}, {"type": "node", "id": 2020712902, "lat": 65.0533892, "lon": 20.0566826}, {"type": "node", "id": 2020712903, "lat": 65.0534482, "lon": 20.0564028}, {"type": "node", "id": 2020712922, "lat": 65.0555639, "lon": 20.0511185}, {"type": "node", "id": 2020712931, "lat": 65.056344, "lon": 20.0491044}, {"type": "node", "id": 2020712963, "lat": 65.0580129, "lon": 20.0449126}, {"type": "node", "id": 2020712995, "lat": 65.0589148, "lon": 20.0412244}, {"type": "node", "id": 2100359074, "lat": 65.0543401, "lon": 20.065359}, {"type": "node", "id": 2100359078, "lat": 65.0548403, "lon": 20.0702878}, {"type": "node", "id": 2100359082, "lat": 65.0551478, "lon": 20.0732451}, {"type": "node", "id": 2100359087, "lat": 65.0554249, "lon": 20.0751858}, {"type": "node", "id": 2100359174, "lat": 65.0563733, "lon": 20.0773319}, {"type": "node", "id": 2100359281, "lat": 65.0582959, "lon": 20.0819218}, {"type": "node", "id": 2100359299, "lat": 65.058664, "lon": 20.0825174}, {"type": "node", "id": 2100359390, "lat": 65.0598273, "lon": 20.1143469}, {"type": "node", "id": 2100359406, "lat": 65.0599067, "lon": 20.084109}, {"type": "node", "id": 2100359419, "lat": 65.0599895, "lon": 20.113011}, {"type": "node", "id": 2100359428, "lat": 65.0600753, "lon": 20.1106948}, {"type": "node", "id": 2100359430, "lat": 65.0601028, "lon": 20.1101466}, {"type": "node", "id": 2100359434, "lat": 65.060138, "lon": 20.1097581}, {"type": "node", "id": 2100359451, "lat": 65.0602804, "lon": 20.1093624}, {"type": "node", "id": 2100359584, "lat": 65.0608651, "lon": 20.1081571}, {"type": "node", "id": 2100359675, "lat": 65.0620369, "lon": 20.0867582}, {"type": "node", "id": 2100359677, "lat": 65.0623309, "lon": 20.1051283}, {"type": "node", "id": 2100359679, "lat": 65.0624525, "lon": 20.0874462}, {"type": "node", "id": 2100359681, "lat": 65.0625171, "lon": 20.1046354}, {"type": "node", "id": 2100359685, "lat": 65.0626167, "lon": 20.104276}, {"type": "node", "id": 2100359689, "lat": 65.062682, "lon": 20.0881547}, {"type": "node", "id": 2100359691, "lat": 65.0628028, "lon": 20.1035059}, {"type": "node", "id": 2100359693, "lat": 65.0628205, "lon": 20.0891199}, {"type": "node", "id": 2100359695, "lat": 65.0630154, "lon": 20.0914714}, {"type": "node", "id": 2100359701, "lat": 65.0632102, "lon": 20.0941514}, {"type": "node", "id": 2100359705, "lat": 65.0634353, "lon": 20.0964002}, {"type": "node", "id": 2100359707, "lat": 65.0635055, "lon": 20.0990237}, {"type": "node", "id": 2100359709, "lat": 65.0635336, "lon": 20.0976786}, {"type": "node", "id": 2100359711, "lat": 65.0635466, "lon": 20.0983666}, {"type": "node", "id": 2910102257, "lat": 65.0620428, "lon": 20.0477948}, {"type": "node", "id": 2910102259, "lat": 65.0623296, "lon": 20.0474294}, {"type": "node", "id": 2910102260, "lat": 65.0629472, "lon": 20.046527}, {"type": "node", "id": 2910102268, "lat": 65.0645748, "lon": 20.0432634}, {"type": "node", "id": 3297226063, "lat": 65.0568225, "lon": 20.0478668}, {"type": "node", "id": 3297226084, "lat": 65.0581632, "lon": 20.0445732}, {"type": "node", "id": 3319315251, "lat": 65.0603238, "lon": 20.0496886}, {"type": "node", "id": 3319315252, "lat": 65.0547775, "lon": 20.0556833}, {"type": "node", "id": 3319315257, "lat": 65.0534114, "lon": 20.0565281}, {"type": "node", "id": 3319315258, "lat": 65.0533843, "lon": 20.0568342}, {"type": "node", "id": 3319315259, "lat": 65.0534052, "lon": 20.0570324}, {"type": "node", "id": 3319315260, "lat": 65.0534458, "lon": 20.0573035}, {"type": "node", "id": 3319315373, "lat": 65.0545301, "lon": 20.0537078}, {"type": "node", "id": 3356009647, "lat": 64.9141977, "lon": 20.3396417}, {"type": "node", "id": 4320991127, "lat": 65.0239735, "lon": 20.1210968}, {"type": "node", "id": 6041601645, "lat": 65.0538113, "lon": 20.0604509}, {"type": "node", "id": 7080291763, "lat": 64.9033795, "lon": 20.3568786}, {"type": "node", "id": 8175305499, "lat": 65.0134761, "lon": 20.1579621}, {"type": "node", "id": 8175305500, "lat": 64.9289415, "lon": 20.3149452}, {"type": "node", "id": 8175305501, "lat": 64.9200509, "lon": 20.3303058}, {"type": "node", "id": 8175305502, "lat": 65.0178237, "lon": 20.1460819}, {"type": "node", "id": 8175305503, "lat": 65.0439607, "lon": 20.0769673}, {"type": "node", "id": 8175305504, "lat": 64.9676862, "lon": 20.2413723}, {"type": "node", "id": 8175305505, "lat": 64.9920445, "lon": 20.2161115}, {"type": "node", "id": 8175305506, "lat": 65.0078758, "lon": 20.1741495}, {"type": "node", "id": 8175305507, "lat": 65.0155258, "lon": 20.1523454}, {"type": "node", "id": 8175305508, "lat": 65.041865, "lon": 20.0808459}, {"type": "node", "id": 8175305509, "lat": 65.0460714, "lon": 20.0725654}, {"type": "node", "id": 8175305510, "lat": 64.9079497, "lon": 20.3463613}, {"type": "node", "id": 8175305511, "lat": 64.906246, "lon": 20.3493355}, {"type": "node", "id": 8177083294, "lat": 65.0446142, "lon": 20.0756375}, {"type": "node", "id": 8177083295, "lat": 64.9580429, "lon": 20.2589277}, {"type": "node", "id": 8177083310, "lat": 64.9340861, "lon": 20.2985207}, {"type": "node", "id": 8177092511, "lat": 64.9827476, "lon": 20.2288712}, {"type": "node", "id": 8758177944, "lat": 65.0015417, "lon": 20.1923937}, {"type": "node", "id": 8758177945, "lat": 65.0006213, "lon": 20.1944938}, {"type": "node", "id": 8758177951, "lat": 65.0025148, "lon": 20.1901376}, {"type": "node", "id": 8758178914, "lat": 64.9552532, "lon": 20.2629304}, {"type": "node", "id": 8758636792, "lat": 64.8994377, "lon": 20.3702643}, {"type": "node", "id": 8758636793, "lat": 64.8985274, "lon": 20.3716242}, {"type": "node", "id": 8758636986, "lat": 64.897158, "lon": 20.3728943}, {"type": "node", "id": 8758637086, "lat": 64.9181917, "lon": 20.3337374}, {"type": "node", "id": 8758637154, "lat": 64.9248833, "lon": 20.322096}, {"type": "node", "id": 8758637156, "lat": 64.9227033, "lon": 20.3255971}, {"type": "node", "id": 9247103359, "lat": 65.0597866, "lon": 20.1145276}, {"type": "node", "id": 9905421929, "lat": 65.049856, "lon": 20.0646318}, {"type": "node", "id": 10156749142, "lat": 65.0545527, "lon": 20.0536512}, {"type": "node", "id": 10156749145, "lat": 65.0543821, "lon": 20.0540758}, {"type": "node", "id": 10156853777, "lat": 65.0585902, "lon": 20.0427732}, {"type": "way", "id": 9923170, "nodes": [81078355, 2910102268, 81078360, 81078365, 81078370, 1834192607, 2910102260, 81078375, 2910102259, 2910102257, 81078380, 3319315251, 81078386, 81078391, 81078396, 3319315252, 81078400, 1418820328, 81078405, 81078408, 81078413, 9905421929, 81078418, 8175305509, 8177083294, 81078422, 8175305503, 81078427, 8175305508, 81078432, 361488883, 81078435, 81078440, 81078442, 81078446, 1852714499, 81078451, 81078456, 81078458, 81078464, 81078469, 81078474, 81078480, 81078483, 1868866249, 4320991127, 81078488, 81078493, 81078498, 81078503, 81078508, 1418823971, 81078514, 81078519, 81078524, 8175305502, 81078528, 81078531, 8175305507, 8175305499, 81078535, 81078540, 81078547, 8175305506, 81078551, 1729491109, 81078556, 81078560, 81078565, 8758177951, 81078570, 8758177944, 8758177945, 81078575, 1729491291, 81078579, 81078584, 8175305505, 81078589, 81292279, 81292280, 81292281, 81292282, 81292283, 8177092511, 81292285, 81292286, 81292287, 81292288, 81292289, 81292290, 81292291, 81292292, 81292293, 1772029064, 81292294, 81292295, 8175305504, 81292296, 81292297, 81292298, 81292300, 1762306953, 81292301, 81292302, 8177083295, 81292303, 8758178914, 81292304, 81292305, 1762303549, 81292306, 81292307, 81292308, 81292309, 81292310, 81292311, 1762201811, 81292312, 81292313, 8177083310, 1762201807, 81292314, 81292315, 81292316, 81292317, 8175305500, 81292318, 81292319, 81292320, 8758637154, 81292321, 8758637156, 81292322, 81292323, 8175305501, 81292324, 8758637086, 81292325, 81292326, 81292327, 81292328, 3356009647, 81292329, 361489243, 81292330, 8175305510, 81292331, 81292332, 8175305511, 81292333, 81292334, 7080291763, 81292335, 81292336, 81292337, 81292338, 81292339, 1769020374, 8758636792, 81292340, 8758636793, 81292341, 8758636986], "tags": {"highway": "primary", "maxspeed": "100", "ref": "95", "surface": "asphalt"}}, {"type": "way", "id": 128365413, "nodes": [1418820340, 1418820339, 2020712995, 10156853777, 1418820338, 3297226084, 2020712963, 1418820337, 1418820333, 3297226063, 2020712931, 2020712922, 10156749142, 3319315373, 10156749145, 1418820326, 2020712903, 3319315257, 2020712902, 3319315258, 3319315259, 3319315260, 1418820328], "tags": {"highway": "tertiary", "maxspeed": "50", "name": "Storgatan", "ref": "AC 844", "reg_ref": "844", "source": "survey"}}, {"type": "way", "id": 200048974, "nodes": [1418820328, 6041601645, 2100359074, 2100359078, 2100359082, 2100359087, 2100359174, 2100359281, 2100359299, 2100359406, 2100359675, 2100359679, 2100359689, 2100359693, 2100359695, 2100359701, 2100359705, 2100359709, 2100359711, 2100359707, 2100359691, 2100359685, 2100359681, 2100359677, 2100359584, 2100359451, 2100359434, 2100359430, 2100359428, 2100359419, 2100359390, 9247103359], "tags": {"highway": "unclassified"}}, {"type": "way", "id": 318126714, "nodes": [1729491109, 1729491289, 1729491357, 1729491721, 1729490975, 1729490949, 1762303460, 1729491709, 1729491739, 1729491849, 1729491534, 1729491788, 1729491182, 1729491403, 1729491169, 1729491345, 1729491253, 1729491418, 1729491837, 1729491131, 1729491122, 1729491694, 1729491294, 1729491691, 1729490954, 1729491244, 1729491651, 1729491479, 1729491078, 1729491465, 1729491135, 1729491781, 1729491142, 1729491111, 1729491580, 1729491127, 1729491307, 1729491036, 1729491486, 1729491188, 1729491751, 1729491227, 1729491755, 1728700220], "tags": {"highway": "tertiary", "ref": "AC 915", "reg_ref": "915", "source": "Bing_imagery"}}]}