{"version": 0.6, "generator": "Overpass API 0.7.62.7 375dc00a", "osm3s": {"timestamp_osm_base": "2025-08-09T02:59:53Z", "copyright": "The data included in this document is from www.openstreetmap.org. The data is made available under ODbL."}, "elements": [{"type": "node", "id": 8224747603, "lat": 56.0498964, "lon": -112.7510762}, {"type": "node", "id": 8225957917, "lat": 56.0498065, "lon": -112.65854}, {"type": "node", "id": 8225957918, "lat": 56.0498005, "lon": -112.6615012}, {"type": "node", "id": 8225957919, "lat": 56.0498724, "lon": -112.7069807}, {"type": "node", "id": 8225957920, "lat": 56.0498484, "lon": -112.6808882}, {"type": "node", "id": 8904586294, "lat": 56.0498009, "lon": -112.6613177}, {"type": "way", "id": 884548607, "nodes": [8224747603, 8225957919, 8225957920, 8225957918, 8904586294, 8225957917], "tags": {"highway": "unclassified", "source": "survey & Esri World Imagery 13-12-20", "surface": "unpaved"}}]}